---- AspectJ Properties ---
AspectJ Compiler 1.8.2 built on Thursday Aug 14, 2014 at 21:45:02 GMT
---- Dump Properties ---
Dump file: ajcore.20210820.012205.637.txt
Dump reason: abort
Dump on exception: true
Dump at exit condition: abort
---- System Properties ---
awt.toolkit=sun.awt.X11.XToolkit
java.specification.version=11
sun.cpu.isalist=
sun.jnu.encoding=UTF-8
java.class.path=argouml-0.35.1/argouml.jar
sun.awt.enableExtraMouseButtons=true
org.aspectj.weaver.loadtime.configuration=file:./configuration/aop.argouml1.xml
java.vm.vendor=Ubuntu
sun.arch.data.model=64
sun.font.fontmanager=sun.awt.X11FontManager
java.vendor.url=https://ubuntu.com/
user.timezone=Europe/Berlin
os.name=Linux
java.vm.specification.version=11
apple.laf.useScreenMenuBar=true
sun.java.launcher=SUN_STANDARD
user.country=DE
sun.boot.library.path=/usr/lib/jvm/java-11-openjdk-amd64/lib
sun.java.command=argouml-0.35.1/argouml.jar
jdk.debug=release
sun.awt.exception.handler=org.argouml.util.logging.AwtExceptionHandler
sun.cpu.endian=little
user.home=/home/jule
user.language=de
java.specification.vendor=Oracle Corporation
java.version.date=2021-04-20
java.home=/usr/lib/jvm/java-11-openjdk-amd64
file.separator=/
java.vm.compressedOopsMode=32-bit
line.separator=

java.specification.name=Java Platform API Specification
java.vm.specification.vendor=Oracle Corporation
java.awt.graphicsenv=sun.awt.X11GraphicsEnvironment
sun.management.compiler=HotSpot 64-Bit Tiered Compilers
kieker.monitoring.configuration=./configuration/kieker.sample.metrics.properties
java.runtime.version=11.0.11+9-Ubuntu-0ubuntu2
user.name=jule
MDRStorageProperty.org.netbeans.mdr.persistence.memoryimpl.id=127-0-1-1-1ddac10b:17b60b81cb7:-8000
path.separator=:
os.version=5.11.0-31-generic
java.runtime.name=OpenJDK Runtime Environment
file.encoding=UTF-8
java.vm.name=OpenJDK 64-Bit Server VM
com.apple.mrj.application.apple.menu.about.name=ArgoUML
gef.imageLocation=/org/argouml/Images
java.vendor.url.bug=https://bugs.launchpad.net/ubuntu/+source/openjdk-lts
java.io.tmpdir=/tmp
org.netbeans.mdr.storagemodel.StorageFactoryClassName=org.netbeans.mdr.persistence.memoryimpl.StorageFactoryImpl
java.version=11.0.11
user.dir=/home/jule/Dokumente/argouml/argouml
os.arch=amd64
java.vm.specification.name=Java Virtual Machine Specification
java.awt.printerjob=sun.print.PSPrinterJob
sun.os.patch.level=unknown
java.library.path=/usr/java/packages/lib:/usr/lib/x86_64-linux-gnu/jni:/lib/x86_64-linux-gnu:/usr/lib/x86_64-linux-gnu:/usr/lib/jni:/lib:/usr/lib
java.vm.info=mixed mode, sharing
java.vendor=Ubuntu
java.vm.version=11.0.11+9-Ubuntu-0ubuntu2
sun.io.unicode.encoding=UnicodeLittle
java.class.version=55.0
---- Command Line ---
Empty
---- Full Classpath ---
Empty
---- Compiler Messages ---
info AspectJ Weaver Version 1.8.2 built on Thursday Aug 14, 2014 at 21:45:02 GMT
info register classloader jdk.internal.loader.ClassLoaders$AppClassLoader@3d4eac69
abort trouble in: 
public class org.argouml.uml.util.namespace.StringNamespace extends java.lang.Object implements org.argouml.uml.util.namespace.Namespace, java.lang.Cloneable:
  private static final java.util.logging.Logger LOG
  private java.util.Stack ns
  private String token
  public void <init>():
                    ALOAD_0     // Lorg/argouml/uml/util/namespace/StringNamespace; this   (line 67)
                    INVOKESPECIAL java.lang.Object.<init> ()V
    constructor-execution(void org.argouml.uml.util.namespace.StringNamespace.<init>())
    |               ALOAD_0     // Lorg/argouml/uml/util/namespace/StringNamespace; this   (line 58)
    |               NEW java.util.Stack
    |               DUP
    |               INVOKESPECIAL java.util.Stack.<init> ()V
    |               PUTFIELD org.argouml.uml.util.namespace.StringNamespace.ns Ljava/util/Stack;
    |               ALOAD_0     // Lorg/argouml/uml/util/namespace/StringNamespace; this   (line 60)
    |               LDC "."
    |               PUTFIELD org.argouml.uml.util.namespace.StringNamespace.token Ljava/lang/String;
    |               RETURN   (line 68)
    constructor-execution(void org.argouml.uml.util.namespace.StringNamespace.<init>())
  end public void <init>()

  public void <init>(String):
                    ALOAD_0     // Lorg/argouml/uml/util/namespace/StringNamespace; this   (line 77)
                    INVOKESPECIAL org.argouml.uml.util.namespace.StringNamespace.<init> ()V
    constructor-execution(void org.argouml.uml.util.namespace.StringNamespace.<init>(java.lang.String))
    |               ALOAD_0     // Lorg/argouml/uml/util/namespace/StringNamespace; this   (line 78)
    |               ALOAD_1     // Ljava/lang/String; theToken
    |               PUTFIELD org.argouml.uml.util.namespace.StringNamespace.token Ljava/lang/String;
    |               RETURN   (line 79)
    constructor-execution(void org.argouml.uml.util.namespace.StringNamespace.<init>(java.lang.String))
  end public void <init>(String)

  public void <init>(String[]):
                    ALOAD_0     // Lorg/argouml/uml/util/namespace/StringNamespace; this   (line 88)
                    ALOAD_1     // [Ljava/lang/String; elements
                    LDC "."
                    INVOKESPECIAL org.argouml.uml.util.namespace.StringNamespace.<init> ([Ljava/lang/String;Ljava/lang/String;)V
    constructor-execution(void org.argouml.uml.util.namespace.StringNamespace.<init>(java.lang.String[]))
    |               RETURN   (line 89)
    constructor-execution(void org.argouml.uml.util.namespace.StringNamespace.<init>(java.lang.String[]))
  end public void <init>(String[])

  public void <init>(String[], String):
                    ALOAD_0     // Lorg/argouml/uml/util/namespace/StringNamespace; this   (line 100)
                    ALOAD_2     // Ljava/lang/String; theToken
                    INVOKESPECIAL org.argouml.uml.util.namespace.StringNamespace.<init> (Ljava/lang/String;)V
    constructor-execution(void org.argouml.uml.util.namespace.StringNamespace.<init>(java.lang.String[], java.lang.String))
    |               ICONST_0   (line 101)
    |               ISTORE_3
    |           L0: ILOAD_3     // I i
    |               ALOAD_1     // [Ljava/lang/String; elements
    |               ARRAYLENGTH
    |               IF_ICMPGE L1
    |               ALOAD_0     // Lorg/argouml/uml/util/namespace/StringNamespace; this   (line 102)
    |               NEW org.argouml.uml.util.namespace.StringNamespaceElement
    |               DUP
    |               ALOAD_1     // [Ljava/lang/String; elements
    |               ILOAD_3     // I i
    |               AALOAD
    |               INVOKESPECIAL org.argouml.uml.util.namespace.StringNamespaceElement.<init> (Ljava/lang/String;)V
    |               ASTORE 4
    |               ASTORE 5
    |               GETSTATIC org.argouml.uml.util.namespace.StringNamespace.ajc$tjp_1 Lorg/aspectj/lang/JoinPoint$StaticPart;
    |               ALOAD_0
    |               ALOAD 5
    |               ALOAD 4
    |               INVOKESTATIC org.aspectj.runtime.reflect.Factory.makeJP (Lorg/aspectj/lang/JoinPoint$StaticPart;Ljava/lang/Object;Ljava/lang/Object;Ljava/lang/Object;)Lorg/aspectj/lang/JoinPoint;
    |               ASTORE 6
    | method-call(void org.argouml.uml.util.namespace.StringNamespace.pushNamespaceElement(org.argouml.uml.util.namespace.NamespaceElement))
    | |             INVOKESTATIC kieker.monitoring.probe.aspectj.flow.operationCall.FullInstrumentation.aspectOf ()Lkieker/monitoring/probe/aspectj/flow/operationCall/FullInstrumentation;
    | |             ALOAD_0
    | |             ALOAD 5
    | |             ICONST_4
    | |             ANEWARRAY java.lang.Object
    | |             ASTORE 8
    | |             ALOAD 8
    | |             ICONST_0
    | |             ALOAD_0
    | |             AASTORE
    | |             ALOAD 8
    | |             ICONST_1
    | |             ALOAD 5
    | |             AASTORE
    | |             ALOAD 8
    | |             ICONST_2
    | |             ALOAD 4
    | |             AASTORE
    | |             ALOAD 8
    | |             ICONST_3
    | |             ALOAD 6
    | |             AASTORE
    | |             NEW org.argouml.uml.util.namespace.StringNamespace$AjcClosure3
    | |             DUP
    | |             ALOAD 8
    | |             INVOKESPECIAL org.argouml.uml.util.namespace.StringNamespace$AjcClosure3.<init> ([Ljava/lang/Object;)V
    | |             SIPUSH 4369
    | |             INVOKEVIRTUAL org.aspectj.runtime.internal.AroundClosure.linkClosureAndJoinPoint (I)Lorg/aspectj/lang/ProceedingJoinPoint;
    | |             GETSTATIC org.argouml.uml.util.namespace.StringNamespace.ajc$tjp_0 Lorg/aspectj/lang/JoinPoint$EnclosingStaticPart;
    | |             INVOKEVIRTUAL kieker.monitoring.probe.aspectj.flow.operationCall.AbstractAspect.member2memberOperation (Ljava/lang/Object;Ljava/lang/Object;Lorg/aspectj/lang/ProceedingJoinPoint;Lorg/aspectj/lang/JoinPoint$EnclosingStaticPart;)Ljava/lang/Object;
    | |             POP
    | method-call(void org.argouml.uml.util.namespace.StringNamespace.pushNamespaceElement(org.argouml.uml.util.namespace.NamespaceElement))
    |               IINC_3 1     // I i   (line 101)
    |               GOTO L0
    |           L1: RETURN   (line 104)
    constructor-execution(void org.argouml.uml.util.namespace.StringNamespace.<init>(java.lang.String[], java.lang.String))
  end public void <init>(String[], String)

  public void <init>(org.argouml.uml.util.namespace.NamespaceElement[], String):
                    ALOAD_0     // Lorg/argouml/uml/util/namespace/StringNamespace; this   (line 115)
                    ALOAD_2     // Ljava/lang/String; theToken
                    INVOKESPECIAL org.argouml.uml.util.namespace.StringNamespace.<init> (Ljava/lang/String;)V
    constructor-execution(void org.argouml.uml.util.namespace.StringNamespace.<init>(org.argouml.uml.util.namespace.NamespaceElement[], java.lang.String))
    |               ICONST_0   (line 117)
    |               ISTORE_3
    |           L0: ILOAD_3     // I i
    |               ALOAD_1     // [Lorg/argouml/uml/util/namespace/NamespaceElement; elements
    |               ARRAYLENGTH
    |               IF_ICMPGE L1
    |               ALOAD_0     // Lorg/argouml/uml/util/namespace/StringNamespace; this   (line 118)
    |               NEW org.argouml.uml.util.namespace.StringNamespaceElement
    |               DUP
    |               ALOAD_1     // [Lorg/argouml/uml/util/namespace/NamespaceElement; elements
    |               ILOAD_3     // I i
    |               AALOAD
    |               ASTORE 4
    |               GETSTATIC org.argouml.uml.util.namespace.StringNamespace.ajc$tjp_3 Lorg/aspectj/lang/JoinPoint$StaticPart;
    |               ALOAD_0
    |               ALOAD 4
    |               INVOKESTATIC org.aspectj.runtime.reflect.Factory.makeJP (Lorg/aspectj/lang/JoinPoint$StaticPart;Ljava/lang/Object;Ljava/lang/Object;)Lorg/aspectj/lang/JoinPoint;
    |               ASTORE 5
    | method-call(java.lang.String java.lang.Object.toString())
    | |             INVOKESTATIC kieker.monitoring.probe.aspectj.flow.operationCall.FullInstrumentation.aspectOf ()Lkieker/monitoring/probe/aspectj/flow/operationCall/FullInstrumentation;
    | |             ALOAD_0
    | |             ALOAD 4
    | |             ICONST_3
    | |             ANEWARRAY java.lang.Object
    | |             ASTORE 7
    | |             ALOAD 7
    | |             ICONST_0
    | |             ALOAD_0
    | |             AASTORE
    | |             ALOAD 7
    | |             ICONST_1
    | |             ALOAD 4
    | |             AASTORE
    | |             ALOAD 7
    | |             ICONST_2
    | |             ALOAD 5
    | |             AASTORE
    | |             NEW org.argouml.uml.util.namespace.StringNamespace$AjcClosure7
    | |             DUP
    | |             ALOAD 7
    | |             INVOKESPECIAL org.argouml.uml.util.namespace.StringNamespace$AjcClosure7.<init> ([Ljava/lang/Object;)V
    | |             SIPUSH 4369
    | |             INVOKEVIRTUAL org.aspectj.runtime.internal.AroundClosure.linkClosureAndJoinPoint (I)Lorg/aspectj/lang/ProceedingJoinPoint;
    | |             GETSTATIC org.argouml.uml.util.namespace.StringNamespace.ajc$tjp_2 Lorg/aspectj/lang/JoinPoint$EnclosingStaticPart;
    | |             INVOKEVIRTUAL kieker.monitoring.probe.aspectj.flow.operationCall.AbstractAspect.member2memberOperation (Ljava/lang/Object;Ljava/lang/Object;Lorg/aspectj/lang/ProceedingJoinPoint;Lorg/aspectj/lang/JoinPoint$EnclosingStaticPart;)Ljava/lang/Object;
    | |             CHECKCAST java.lang.String
    | method-call(java.lang.String java.lang.Object.toString())
    |               INVOKESPECIAL org.argouml.uml.util.namespace.StringNamespaceElement.<init> (Ljava/lang/String;)V
    |               ASTORE 8
    |               ASTORE 9
    |               GETSTATIC org.argouml.uml.util.namespace.StringNamespace.ajc$tjp_4 Lorg/aspectj/lang/JoinPoint$StaticPart;
    |               ALOAD_0
    |               ALOAD 9
    |               ALOAD 8
    |               INVOKESTATIC org.aspectj.runtime.reflect.Factory.makeJP (Lorg/aspectj/lang/JoinPoint$StaticPart;Ljava/lang/Object;Ljava/lang/Object;Ljava/lang/Object;)Lorg/aspectj/lang/JoinPoint;
    |               ASTORE 10
    | method-call(void org.argouml.uml.util.namespace.StringNamespace.pushNamespaceElement(org.argouml.uml.util.namespace.NamespaceElement))
    | |             INVOKESTATIC kieker.monitoring.probe.aspectj.flow.operationCall.FullInstrumentation.aspectOf ()Lkieker/monitoring/probe/aspectj/flow/operationCall/FullInstrumentation;
    | |             ALOAD_0
    | |             ALOAD 9
    | |             ICONST_4
    | |             ANEWARRAY java.lang.Object
    | |             ASTORE 12
    | |             ALOAD 12
    | |             ICONST_0
    | |             ALOAD_0
    | |             AASTORE
    | |             ALOAD 12
    | |             ICONST_1
    | |             ALOAD 9
    | |             AASTORE
    | |             ALOAD 12
    | |             ICONST_2
    | |             ALOAD 8
    | |             AASTORE
    | |             ALOAD 12
    | |             ICONST_3
    | |             ALOAD 10
    | |             AASTORE
    | |             NEW org.argouml.uml.util.namespace.StringNamespace$AjcClosure11
    | |             DUP
    | |             ALOAD 12
    | |             INVOKESPECIAL org.argouml.uml.util.namespace.StringNamespace$AjcClosure11.<init> ([Ljava/lang/Object;)V
    | |             SIPUSH 4369
    | |             INVOKEVIRTUAL org.aspectj.runtime.internal.AroundClosure.linkClosureAndJoinPoint (I)Lorg/aspectj/lang/ProceedingJoinPoint;
    | |             GETSTATIC org.argouml.uml.util.namespace.StringNamespace.ajc$tjp_2 Lorg/aspectj/lang/JoinPoint$EnclosingStaticPart;
    | |             INVOKEVIRTUAL kieker.monitoring.probe.aspectj.flow.operationCall.AbstractAspect.member2memberOperation (Ljava/lang/Object;Ljava/lang/Object;Lorg/aspectj/lang/ProceedingJoinPoint;Lorg/aspectj/lang/JoinPoint$EnclosingStaticPart;)Ljava/lang/Object;
    | |             POP
    | method-call(void org.argouml.uml.util.namespace.StringNamespace.pushNamespaceElement(org.argouml.uml.util.namespace.NamespaceElement))
    |               IINC_3 1     // I i   (line 117)
    |               GOTO L0
    |           L1: RETURN   (line 121)
    constructor-execution(void org.argouml.uml.util.namespace.StringNamespace.<init>(org.argouml.uml.util.namespace.NamespaceElement[], java.lang.String))
  end public void <init>(org.argouml.uml.util.namespace.NamespaceElement[], String)

  public void <init>(org.argouml.uml.util.namespace.NamespaceElement[]):
                    ALOAD_0     // Lorg/argouml/uml/util/namespace/StringNamespace; this   (line 130)
                    ALOAD_1     // [Lorg/argouml/uml/util/namespace/NamespaceElement; elements
                    LDC "."
                    INVOKESPECIAL org.argouml.uml.util.namespace.StringNamespace.<init> ([Lorg/argouml/uml/util/namespace/NamespaceElement;Ljava/lang/String;)V
    constructor-execution(void org.argouml.uml.util.namespace.StringNamespace.<init>(org.argouml.uml.util.namespace.NamespaceElement[]))
    |               RETURN   (line 131)
    constructor-execution(void org.argouml.uml.util.namespace.StringNamespace.<init>(org.argouml.uml.util.namespace.NamespaceElement[]))
  end public void <init>(org.argouml.uml.util.namespace.NamespaceElement[])

  public void pushNamespaceElement(org.argouml.uml.util.namespace.NamespaceElement):
                    ALOAD_1
                    ASTORE 7
                    GETSTATIC org.argouml.uml.util.namespace.StringNamespace.ajc$tjp_5 Lorg/aspectj/lang/JoinPoint$EnclosingStaticPart;
                    ALOAD_0
                    ALOAD_0
                    ALOAD 7
                    INVOKESTATIC org.aspectj.runtime.reflect.Factory.makeJP (Lorg/aspectj/lang/JoinPoint$StaticPart;Ljava/lang/Object;Ljava/lang/Object;Ljava/lang/Object;)Lorg/aspectj/lang/JoinPoint;
                    ASTORE 8
    method-execution(void org.argouml.uml.util.namespace.StringNamespace.pushNamespaceElement(org.argouml.uml.util.namespace.NamespaceElement))
    |               INVOKESTATIC kieker.monitoring.probe.aspectj.flow.operationExecution.FullInstrumentation.aspectOf ()Lkieker/monitoring/probe/aspectj/flow/operationExecution/FullInstrumentation;   (line 137)
    |               ALOAD_0
    |               ICONST_3
    |               ANEWARRAY java.lang.Object
    |               ASTORE 9
    |               ALOAD 9
    |               ICONST_0
    |               ALOAD_0
    |               AASTORE
    |               ALOAD 9
    |               ICONST_1
    |               ALOAD 7
    |               AASTORE
    |               ALOAD 9
    |               ICONST_2
    |               ALOAD 8
    |               AASTORE
    |               NEW org.argouml.uml.util.namespace.StringNamespace$AjcClosure17
    |               DUP
    |               ALOAD 9
    |               INVOKESPECIAL org.argouml.uml.util.namespace.StringNamespace$AjcClosure17.<init> ([Ljava/lang/Object;)V
    |               LDC_W 69904
    |               INVOKEVIRTUAL org.aspectj.runtime.internal.AroundClosure.linkClosureAndJoinPoint (I)Lorg/aspectj/lang/ProceedingJoinPoint;
    |               INVOKEVIRTUAL kieker.monitoring.probe.aspectj.flow.operationExecution.AbstractAspect.operation (Ljava/lang/Object;Lorg/aspectj/lang/ProceedingJoinPoint;)Ljava/lang/Object;
    |               POP
    |               RETURN
    method-execution(void org.argouml.uml.util.namespace.StringNamespace.pushNamespaceElement(org.argouml.uml.util.namespace.NamespaceElement))
  end public void pushNamespaceElement(org.argouml.uml.util.namespace.NamespaceElement)

  public org.argouml.uml.util.namespace.NamespaceElement peekNamespaceElement():
                    GETSTATIC org.argouml.uml.util.namespace.StringNamespace.ajc$tjp_7 Lorg/aspectj/lang/JoinPoint$EnclosingStaticPart;
                    ALOAD_0
                    ALOAD_0
                    INVOKESTATIC org.aspectj.runtime.reflect.Factory.makeJP (Lorg/aspectj/lang/JoinPoint$StaticPart;Ljava/lang/Object;Ljava/lang/Object;)Lorg/aspectj/lang/JoinPoint;
                    ASTORE 5
    method-execution(org.argouml.uml.util.namespace.NamespaceElement org.argouml.uml.util.namespace.StringNamespace.peekNamespaceElement())
    |               INVOKESTATIC kieker.monitoring.probe.aspectj.flow.operationExecution.FullInstrumentation.aspectOf ()Lkieker/monitoring/probe/aspectj/flow/operationExecution/FullInstrumentation;   (line 144)
    |               ALOAD_0
    |               ICONST_2
    |               ANEWARRAY java.lang.Object
    |               ASTORE 6
    |               ALOAD 6
    |               ICONST_0
    |               ALOAD_0
    |               AASTORE
    |               ALOAD 6
    |               ICONST_1
    |               ALOAD 5
    |               AASTORE
    |               NEW org.argouml.uml.util.namespace.StringNamespace$AjcClosure23
    |               DUP
    |               ALOAD 6
    |               INVOKESPECIAL org.argouml.uml.util.namespace.StringNamespace$AjcClosure23.<init> ([Ljava/lang/Object;)V
    |               LDC_W 69904
    |               INVOKEVIRTUAL org.aspectj.runtime.internal.AroundClosure.linkClosureAndJoinPoint (I)Lorg/aspectj/lang/ProceedingJoinPoint;
    |               INVOKEVIRTUAL kieker.monitoring.probe.aspectj.flow.operationExecution.AbstractAspect.operation (Ljava/lang/Object;Lorg/aspectj/lang/ProceedingJoinPoint;)Ljava/lang/Object;
    |               CHECKCAST org.argouml.uml.util.namespace.NamespaceElement
    |               ARETURN
    method-execution(org.argouml.uml.util.namespace.NamespaceElement org.argouml.uml.util.namespace.StringNamespace.peekNamespaceElement())
  end public org.argouml.uml.util.namespace.NamespaceElement peekNamespaceElement()

  public void pushNamespaceElement(String):
                    ALOAD_1
                    ASTORE 7
                    GETSTATIC org.argouml.uml.util.namespace.StringNamespace.ajc$tjp_9 Lorg/aspectj/lang/JoinPoint$EnclosingStaticPart;
                    ALOAD_0
                    ALOAD_0
                    ALOAD 7
                    INVOKESTATIC org.aspectj.runtime.reflect.Factory.makeJP (Lorg/aspectj/lang/JoinPoint$StaticPart;Ljava/lang/Object;Ljava/lang/Object;Ljava/lang/Object;)Lorg/aspectj/lang/JoinPoint;
                    ASTORE 8
    method-execution(void org.argouml.uml.util.namespace.StringNamespace.pushNamespaceElement(java.lang.String))
    |               INVOKESTATIC kieker.monitoring.probe.aspectj.flow.operationExecution.FullInstrumentation.aspectOf ()Lkieker/monitoring/probe/aspectj/flow/operationExecution/FullInstrumentation;   (line 154)
    |               ALOAD_0
    |               ICONST_3
    |               ANEWARRAY java.lang.Object
    |               ASTORE 9
    |               ALOAD 9
    |               ICONST_0
    |               ALOAD_0
    |               AASTORE
    |               ALOAD 9
    |               ICONST_1
    |               ALOAD 7
    |               AASTORE
    |               ALOAD 9
    |               ICONST_2
    |               ALOAD 8
    |               AASTORE
    |               NEW org.argouml.uml.util.namespace.StringNamespace$AjcClosure29
    |               DUP
    |               ALOAD 9
    |               INVOKESPECIAL org.argouml.uml.util.namespace.StringNamespace$AjcClosure29.<init> ([Ljava/lang/Object;)V
    |               LDC_W 69904
    |               INVOKEVIRTUAL org.aspectj.runtime.internal.AroundClosure.linkClosureAndJoinPoint (I)Lorg/aspectj/lang/ProceedingJoinPoint;
    |               INVOKEVIRTUAL kieker.monitoring.probe.aspectj.flow.operationExecution.AbstractAspect.operation (Ljava/lang/Object;Lorg/aspectj/lang/ProceedingJoinPoint;)Ljava/lang/Object;
    |               POP
    |               RETURN
    method-execution(void org.argouml.uml.util.namespace.StringNamespace.pushNamespaceElement(java.lang.String))
  end public void pushNamespaceElement(String)

  public org.argouml.uml.util.namespace.NamespaceElement popNamespaceElement():
                    GETSTATIC org.argouml.uml.util.namespace.StringNamespace.ajc$tjp_11 Lorg/aspectj/lang/JoinPoint$EnclosingStaticPart;
                    ALOAD_0
                    ALOAD_0
                    INVOKESTATIC org.aspectj.runtime.reflect.Factory.makeJP (Lorg/aspectj/lang/JoinPoint$StaticPart;Ljava/lang/Object;Ljava/lang/Object;)Lorg/aspectj/lang/JoinPoint;
                    ASTORE 5
    method-execution(org.argouml.uml.util.namespace.NamespaceElement org.argouml.uml.util.namespace.StringNamespace.popNamespaceElement())
    |               INVOKESTATIC kieker.monitoring.probe.aspectj.flow.operationExecution.FullInstrumentation.aspectOf ()Lkieker/monitoring/probe/aspectj/flow/operationExecution/FullInstrumentation;   (line 161)
    |               ALOAD_0
    |               ICONST_2
    |               ANEWARRAY java.lang.Object
    |               ASTORE 6
    |               ALOAD 6
    |               ICONST_0
    |               ALOAD_0
    |               AASTORE
    |               ALOAD 6
    |               ICONST_1
    |               ALOAD 5
    |               AASTORE
    |               NEW org.argouml.uml.util.namespace.StringNamespace$AjcClosure35
    |               DUP
    |               ALOAD 6
    |               INVOKESPECIAL org.argouml.uml.util.namespace.StringNamespace$AjcClosure35.<init> ([Ljava/lang/Object;)V
    |               LDC_W 69904
    |               INVOKEVIRTUAL org.aspectj.runtime.internal.AroundClosure.linkClosureAndJoinPoint (I)Lorg/aspectj/lang/ProceedingJoinPoint;
    |               INVOKEVIRTUAL kieker.monitoring.probe.aspectj.flow.operationExecution.AbstractAspect.operation (Ljava/lang/Object;Lorg/aspectj/lang/ProceedingJoinPoint;)Ljava/lang/Object;
    |               CHECKCAST org.argouml.uml.util.namespace.NamespaceElement
    |               ARETURN
    method-execution(org.argouml.uml.util.namespace.NamespaceElement org.argouml.uml.util.namespace.StringNamespace.popNamespaceElement())
  end public org.argouml.uml.util.namespace.NamespaceElement popNamespaceElement()

  public org.argouml.uml.util.namespace.Namespace getBaseNamespace():
    method-execution(org.argouml.uml.util.namespace.Namespace org.argouml.uml.util.namespace.StringNamespace.getBaseNamespace())
    |               ACONST_NULL   (line 168)
    |               ASTORE_1
    | catch java.lang.CloneNotSupportedException -> E0
    | |             ALOAD_0     // Lorg/argouml/uml/util/namespace/StringNamespace; this   (line 170)
    | |             ASTORE_3
    | |             GETSTATIC org.argouml.uml.util.namespace.StringNamespace.ajc$tjp_14 Lorg/aspectj/lang/JoinPoint$StaticPart;
    | |             ALOAD_0
    | |             ALOAD_3
    | |             INVOKESTATIC org.aspectj.runtime.reflect.Factory.makeJP (Lorg/aspectj/lang/JoinPoint$StaticPart;Ljava/lang/Object;Ljava/lang/Object;)Lorg/aspectj/lang/JoinPoint;
    | |             ASTORE 4
    | | method-call(java.lang.Object java.lang.Object.clone())
    | | |           ALOAD_3
    | | |           INVOKEVIRTUAL java.lang.Object.clone ()Ljava/lang/Object;
    | | method-call(java.lang.Object java.lang.Object.clone())
    | |             CHECKCAST org.argouml.uml.util.namespace.StringNamespace
    | |             ASTORE_1     // Lorg/argouml/uml/util/namespace/StringNamespace; result
    | catch java.lang.CloneNotSupportedException -> E0
    |               GOTO L0   (line 174)
    |           E0: ASTORE_2   (line 171)
    |               GETSTATIC org.argouml.uml.util.namespace.StringNamespace.LOG Ljava/util/logging/Logger;   (line 172)
    |               GETSTATIC java.util.logging.Level.FINE Ljava/util/logging/Level;
    |               LDC ""
    |               ALOAD_2     // Ljava/lang/CloneNotSupportedException; e
    | method-call(void java.util.logging.Logger.log(java.util.logging.Level, java.lang.String, java.lang.Throwable))
    | |             INVOKEVIRTUAL java.util.logging.Logger.log (Ljava/util/logging/Level;Ljava/lang/String;Ljava/lang/Throwable;)V
    | method-call(void java.util.logging.Logger.log(java.util.logging.Level, java.lang.String, java.lang.Throwable))
    |               ACONST_NULL   (line 173)
    |               ARETURN
    |           L0: ALOAD_1     // Lorg/argouml/uml/util/namespace/StringNamespace; result   (line 175)
    | method-call(org.argouml.uml.util.namespace.NamespaceElement org.argouml.uml.util.namespace.StringNamespace.popNamespaceElement())
    | |             INVOKEVIRTUAL org.argouml.uml.util.namespace.StringNamespace.popNamespaceElement ()Lorg/argouml/uml/util/namespace/NamespaceElement;
    | method-call(org.argouml.uml.util.namespace.NamespaceElement org.argouml.uml.util.namespace.StringNamespace.popNamespaceElement())
    |               POP
    |               ALOAD_1     // Lorg/argouml/uml/util/namespace/StringNamespace; result   (line 176)
    |               ARETURN
    method-execution(org.argouml.uml.util.namespace.Namespace org.argouml.uml.util.namespace.StringNamespace.getBaseNamespace())
  end public org.argouml.uml.util.namespace.Namespace getBaseNamespace()

  public org.argouml.uml.util.namespace.Namespace getCommonNamespace(org.argouml.uml.util.namespace.Namespace):
    method-execution(org.argouml.uml.util.namespace.Namespace org.argouml.uml.util.namespace.StringNamespace.getCommonNamespace(org.argouml.uml.util.namespace.Namespace))
    |               ALOAD_0     // Lorg/argouml/uml/util/namespace/StringNamespace; this   (line 184)
    | method-call(java.util.Iterator org.argouml.uml.util.namespace.StringNamespace.iterator())
    | |             INVOKEVIRTUAL org.argouml.uml.util.namespace.StringNamespace.iterator ()Ljava/util/Iterator;
    | method-call(java.util.Iterator org.argouml.uml.util.namespace.StringNamespace.iterator())
    |               ASTORE_2
    |               ALOAD_1     // Lorg/argouml/uml/util/namespace/Namespace; namespace   (line 185)
    | method-call(java.util.Iterator org.argouml.uml.util.namespace.Namespace.iterator())
    | |             INVOKEINTERFACE org.argouml.uml.util.namespace.Namespace.iterator ()Ljava/util/Iterator;
    | method-call(java.util.Iterator org.argouml.uml.util.namespace.Namespace.iterator())
    |               ASTORE_3
    |               NEW org.argouml.uml.util.namespace.StringNamespace   (line 186)
    |               DUP
    |               ALOAD_0     // Lorg/argouml/uml/util/namespace/StringNamespace; this
    |               GETFIELD org.argouml.uml.util.namespace.StringNamespace.token Ljava/lang/String;
    |               INVOKESPECIAL org.argouml.uml.util.namespace.StringNamespace.<init> (Ljava/lang/String;)V
    |               ASTORE 4
    |           L0: ALOAD_2     // Ljava/util/Iterator; i   (line 188)
    | method-call(boolean java.util.Iterator.hasNext())
    | |             INVOKEINTERFACE java.util.Iterator.hasNext ()Z
    | method-call(boolean java.util.Iterator.hasNext())
    |               IFEQ L2
    |               ALOAD_3     // Ljava/util/Iterator; j
    | method-call(boolean java.util.Iterator.hasNext())
    | |             INVOKEINTERFACE java.util.Iterator.hasNext ()Z
    | method-call(boolean java.util.Iterator.hasNext())
    |               IFEQ L2
    |               ALOAD_2     // Ljava/util/Iterator; i   (line 189)
    | method-call(java.lang.Object java.util.Iterator.next())
    | |             INVOKEINTERFACE java.util.Iterator.next ()Ljava/lang/Object;
    | method-call(java.lang.Object java.util.Iterator.next())
    |               CHECKCAST org.argouml.uml.util.namespace.NamespaceElement
    |               ASTORE 5
    |               ALOAD_3     // Ljava/util/Iterator; j   (line 190)
    | method-call(java.lang.Object java.util.Iterator.next())
    | |             INVOKEINTERFACE java.util.Iterator.next ()Ljava/lang/Object;
    | method-call(java.lang.Object java.util.Iterator.next())
    |               CHECKCAST org.argouml.uml.util.namespace.NamespaceElement
    |               ASTORE 6
    |               ALOAD 5     // Lorg/argouml/uml/util/namespace/NamespaceElement; elem1   (line 191)
    | method-call(java.lang.String java.lang.Object.toString())
    | |             INVOKEVIRTUAL java.lang.Object.toString ()Ljava/lang/String;
    | method-call(java.lang.String java.lang.Object.toString())
    |               ALOAD 6     // Lorg/argouml/uml/util/namespace/NamespaceElement; elem2
    | method-call(java.lang.String java.lang.Object.toString())
    | |             INVOKEVIRTUAL java.lang.Object.toString ()Ljava/lang/String;
    | method-call(java.lang.String java.lang.Object.toString())
    | method-call(boolean java.lang.String.equals(java.lang.Object))
    | |             INVOKEVIRTUAL java.lang.String.equals (Ljava/lang/Object;)Z
    | method-call(boolean java.lang.String.equals(java.lang.Object))
    |               IFEQ L1
    |               ALOAD 4     // Lorg/argouml/uml/util/namespace/StringNamespace; result   (line 192)
    |               ALOAD 5     // Lorg/argouml/uml/util/namespace/NamespaceElement; elem1
    | method-call(void org.argouml.uml.util.namespace.StringNamespace.pushNamespaceElement(org.argouml.uml.util.namespace.NamespaceElement))
    | |             INVOKEVIRTUAL org.argouml.uml.util.namespace.StringNamespace.pushNamespaceElement (Lorg/argouml/uml/util/namespace/NamespaceElement;)V
    | method-call(void org.argouml.uml.util.namespace.StringNamespace.pushNamespaceElement(org.argouml.uml.util.namespace.NamespaceElement))
    |           L1: GOTO L0   (line 194)
    |           L2: ALOAD 4     // Lorg/argouml/uml/util/namespace/StringNamespace; result   (line 196)
    |               ARETURN
    method-execution(org.argouml.uml.util.namespace.Namespace org.argouml.uml.util.namespace.StringNamespace.getCommonNamespace(org.argouml.uml.util.namespace.Namespace))
  end public org.argouml.uml.util.namespace.Namespace getCommonNamespace(org.argouml.uml.util.namespace.Namespace)

  public java.util.Iterator iterator():
    method-execution(java.util.Iterator org.argouml.uml.util.namespace.StringNamespace.iterator())
    |               ALOAD_0     // Lorg/argouml/uml/util/namespace/StringNamespace; this   (line 203)
    |               GETFIELD org.argouml.uml.util.namespace.StringNamespace.ns Ljava/util/Stack;
    | method-call(java.util.Iterator java.util.Stack.iterator())
    | |             INVOKEVIRTUAL java.util.Stack.iterator ()Ljava/util/Iterator;
    | method-call(java.util.Iterator java.util.Stack.iterator())
    |               ARETURN
    method-execution(java.util.Iterator org.argouml.uml.util.namespace.StringNamespace.iterator())
  end public java.util.Iterator iterator()

  public boolean isEmpty():
    method-execution(boolean org.argouml.uml.util.namespace.StringNamespace.isEmpty())
    |               ALOAD_0     // Lorg/argouml/uml/util/namespace/StringNamespace; this   (line 210)
    |               GETFIELD org.argouml.uml.util.namespace.StringNamespace.ns Ljava/util/Stack;
    | method-call(boolean java.util.Stack.isEmpty())
    | |             INVOKEVIRTUAL java.util.Stack.isEmpty ()Z
    | method-call(boolean java.util.Stack.isEmpty())
    |               IRETURN
    method-execution(boolean org.argouml.uml.util.namespace.StringNamespace.isEmpty())
  end public boolean isEmpty()

  public void setDefaultScopeToken(String):
    method-execution(void org.argouml.uml.util.namespace.StringNamespace.setDefaultScopeToken(java.lang.String))
    |               ALOAD_0     // Lorg/argouml/uml/util/namespace/StringNamespace; this   (line 217)
    |               ALOAD_1     // Ljava/lang/String; theToken
    |               PUTFIELD org.argouml.uml.util.namespace.StringNamespace.token Ljava/lang/String;
    |               RETURN   (line 218)
    method-execution(void org.argouml.uml.util.namespace.StringNamespace.setDefaultScopeToken(java.lang.String))
  end public void setDefaultScopeToken(String)

  public static org.argouml.uml.util.namespace.Namespace parse(String, String):
    method-execution(org.argouml.uml.util.namespace.Namespace org.argouml.uml.util.namespace.StringNamespace.parse(java.lang.String, java.lang.String))
    |               ALOAD_0     // Ljava/lang/String; fqn   (line 231)
    |               ASTORE_2
    |               NEW org.argouml.uml.util.namespace.StringNamespace   (line 232)
    |               DUP
    |               ALOAD_1     // Ljava/lang/String; token
    |               INVOKESPECIAL org.argouml.uml.util.namespace.StringNamespace.<init> (Ljava/lang/String;)V
    |               ASTORE_3
    |               ALOAD_2     // Ljava/lang/String; myFqn   (line 233)
    |               ALOAD_1     // Ljava/lang/String; token
    | method-call(int java.lang.String.indexOf(java.lang.String))
    | |             INVOKEVIRTUAL java.lang.String.indexOf (Ljava/lang/String;)I
    | method-call(int java.lang.String.indexOf(java.lang.String))
    |               ISTORE 4
    |           L0: ILOAD 4     // I i   (line 234)
    |               ICONST_M1
    |               IF_ICMPLE L1
    |               ALOAD_3     // Lorg/argouml/uml/util/namespace/StringNamespace; sns   (line 235)
    |               ALOAD_2     // Ljava/lang/String; myFqn
    |               ICONST_0
    |               ILOAD 4     // I i
    | method-call(java.lang.String java.lang.String.substring(int, int))
    | |             INVOKEVIRTUAL java.lang.String.substring (II)Ljava/lang/String;
    | method-call(java.lang.String java.lang.String.substring(int, int))
    | method-call(void org.argouml.uml.util.namespace.StringNamespace.pushNamespaceElement(java.lang.String))
    | |             INVOKEVIRTUAL org.argouml.uml.util.namespace.StringNamespace.pushNamespaceElement (Ljava/lang/String;)V
    | method-call(void org.argouml.uml.util.namespace.StringNamespace.pushNamespaceElement(java.lang.String))
    |               ALOAD_2     // Ljava/lang/String; myFqn   (line 236)
    |               ILOAD 4     // I i
    |               ALOAD_1     // Ljava/lang/String; token
    | method-call(int java.lang.String.length())
    | |             INVOKEVIRTUAL java.lang.String.length ()I
    | method-call(int java.lang.String.length())
    |               IADD
    | method-call(java.lang.String java.lang.String.substring(int))
    | |             INVOKEVIRTUAL java.lang.String.substring (I)Ljava/lang/String;
    | method-call(java.lang.String java.lang.String.substring(int))
    |               ASTORE_2     // Ljava/lang/String; myFqn
    |               ALOAD_2     // Ljava/lang/String; myFqn   (line 237)
    |               ALOAD_1     // Ljava/lang/String; token
    | method-call(int java.lang.String.indexOf(java.lang.String))
    | |             INVOKEVIRTUAL java.lang.String.indexOf (Ljava/lang/String;)I
    | method-call(int java.lang.String.indexOf(java.lang.String))
    |               ISTORE 4     // I i
    |               GOTO L0
    |           L1: ALOAD_2     // Ljava/lang/String; myFqn   (line 239)
    | method-call(int java.lang.String.length())
    | |             INVOKEVIRTUAL java.lang.String.length ()I
    | method-call(int java.lang.String.length())
    |               IFLE L2
    |               ALOAD_3     // Lorg/argouml/uml/util/namespace/StringNamespace; sns   (line 240)
    |               ALOAD_2     // Ljava/lang/String; myFqn
    | method-call(void org.argouml.uml.util.namespace.StringNamespace.pushNamespaceElement(java.lang.String))
    | |             INVOKEVIRTUAL org.argouml.uml.util.namespace.StringNamespace.pushNamespaceElement (Ljava/lang/String;)V
    | method-call(void org.argouml.uml.util.namespace.StringNamespace.pushNamespaceElement(java.lang.String))
    |           L2: ALOAD_3     // Lorg/argouml/uml/util/namespace/StringNamespace; sns   (line 242)
    |               ARETURN
    method-execution(org.argouml.uml.util.namespace.Namespace org.argouml.uml.util.namespace.StringNamespace.parse(java.lang.String, java.lang.String))
  end public static org.argouml.uml.util.namespace.Namespace parse(String, String)

  public static org.argouml.uml.util.namespace.Namespace parse(Class):
    method-execution(org.argouml.uml.util.namespace.Namespace org.argouml.uml.util.namespace.StringNamespace.parse(java.lang.Class))
    |               ALOAD_0     // Ljava/lang/Class; c   (line 253)
    | method-call(java.lang.String java.lang.Class.getName())
    | |             INVOKEVIRTUAL java.lang.Class.getName ()Ljava/lang/String;
    | method-call(java.lang.String java.lang.Class.getName())
    |               LDC "."
    | method-call(org.argouml.uml.util.namespace.Namespace org.argouml.uml.util.namespace.StringNamespace.parse(java.lang.String, java.lang.String))
    | |             INVOKESTATIC org.argouml.uml.util.namespace.StringNamespace.parse (Ljava/lang/String;Ljava/lang/String;)Lorg/argouml/uml/util/namespace/Namespace;
    | method-call(org.argouml.uml.util.namespace.Namespace org.argouml.uml.util.namespace.StringNamespace.parse(java.lang.String, java.lang.String))
    |               ARETURN
    method-execution(org.argouml.uml.util.namespace.Namespace org.argouml.uml.util.namespace.StringNamespace.parse(java.lang.Class))
  end public static org.argouml.uml.util.namespace.Namespace parse(Class)

  public int hashCode():
    method-execution(int org.argouml.uml.util.namespace.StringNamespace.hashCode())
    |               ALOAD_0     // Lorg/argouml/uml/util/namespace/StringNamespace; this   (line 260)
    |               LDC "."
    | method-call(java.lang.String org.argouml.uml.util.namespace.StringNamespace.toString(java.lang.String))
    | |             INVOKEVIRTUAL org.argouml.uml.util.namespace.StringNamespace.toString (Ljava/lang/String;)Ljava/lang/String;
    | method-call(java.lang.String org.argouml.uml.util.namespace.StringNamespace.toString(java.lang.String))
    | method-call(int java.lang.String.hashCode())
    | |             INVOKEVIRTUAL java.lang.String.hashCode ()I
    | method-call(int java.lang.String.hashCode())
    |               IRETURN
    method-execution(int org.argouml.uml.util.namespace.StringNamespace.hashCode())
  end public int hashCode()

  public boolean equals(Object):
    method-execution(boolean org.argouml.uml.util.namespace.StringNamespace.equals(java.lang.Object))
    |               ALOAD_1     // Ljava/lang/Object; namespace   (line 274)
    |               INSTANCEOF org.argouml.uml.util.namespace.Namespace
    |               IFEQ L0
    |               ALOAD_0     // Lorg/argouml/uml/util/namespace/StringNamespace; this   (line 275)
    |               LDC "."
    | method-call(java.lang.String org.argouml.uml.util.namespace.StringNamespace.toString(java.lang.String))
    | |             INVOKEVIRTUAL org.argouml.uml.util.namespace.StringNamespace.toString (Ljava/lang/String;)Ljava/lang/String;
    | method-call(java.lang.String org.argouml.uml.util.namespace.StringNamespace.toString(java.lang.String))
    |               ASTORE_2
    |               ALOAD_1     // Ljava/lang/Object; namespace   (line 276)
    |               CHECKCAST org.argouml.uml.util.namespace.Namespace
    |               LDC "."
    | method-call(java.lang.String org.argouml.uml.util.namespace.Namespace.toString(java.lang.String))
    | |             INVOKEINTERFACE org.argouml.uml.util.namespace.Namespace.toString (Ljava/lang/String;)Ljava/lang/String;
    | method-call(java.lang.String org.argouml.uml.util.namespace.Namespace.toString(java.lang.String))
    |               ASTORE_3
    |               ALOAD_2     // Ljava/lang/String; ns1   (line 277)
    |               ALOAD_3     // Ljava/lang/String; ns2
    | method-call(boolean java.lang.String.equals(java.lang.Object))
    | |             INVOKEVIRTUAL java.lang.String.equals (Ljava/lang/Object;)Z
    | method-call(boolean java.lang.String.equals(java.lang.Object))
    |               IRETURN
    |           L0: ICONST_0   (line 279)
    |               IRETURN
    method-execution(boolean org.argouml.uml.util.namespace.StringNamespace.equals(java.lang.Object))
  end public boolean equals(Object)

  public String toString(String):
    method-execution(java.lang.String org.argouml.uml.util.namespace.StringNamespace.toString(java.lang.String))
    |               NEW java.lang.StringBuffer   (line 286)
    |               DUP
    |               INVOKESPECIAL java.lang.StringBuffer.<init> ()V
    |               ASTORE_2
    |               ALOAD_0     // Lorg/argouml/uml/util/namespace/StringNamespace; this   (line 287)
    |               GETFIELD org.argouml.uml.util.namespace.StringNamespace.ns Ljava/util/Stack;
    | method-call(java.util.Iterator java.util.Stack.iterator())
    | |             INVOKEVIRTUAL java.util.Stack.iterator ()Ljava/util/Iterator;
    | method-call(java.util.Iterator java.util.Stack.iterator())
    |               ASTORE_3
    |           L0: ALOAD_3     // Ljava/util/Iterator; i   (line 288)
    | method-call(boolean java.util.Iterator.hasNext())
    | |             INVOKEINTERFACE java.util.Iterator.hasNext ()Z
    | method-call(boolean java.util.Iterator.hasNext())
    |               IFEQ L1
    |               ALOAD_2     // Ljava/lang/StringBuffer; result   (line 289)
    |               ALOAD_3     // Ljava/util/Iterator; i
    | method-call(java.lang.Object java.util.Iterator.next())
    | |             INVOKEINTERFACE java.util.Iterator.next ()Ljava/lang/Object;
    | method-call(java.lang.Object java.util.Iterator.next())
    | method-call(java.lang.StringBuffer java.lang.StringBuffer.append(java.lang.Object))
    | |             INVOKEVIRTUAL java.lang.StringBuffer.append (Ljava/lang/Object;)Ljava/lang/StringBuffer;
    | method-call(java.lang.StringBuffer java.lang.StringBuffer.append(java.lang.Object))
    |               POP
    |               ALOAD_3     // Ljava/util/Iterator; i   (line 290)
    | method-call(boolean java.util.Iterator.hasNext())
    | |             INVOKEINTERFACE java.util.Iterator.hasNext ()Z
    | method-call(boolean java.util.Iterator.hasNext())
    |               IFEQ L0
    |               ALOAD_2     // Ljava/lang/StringBuffer; result   (line 291)
    |               ALOAD_1     // Ljava/lang/String; theToken
    | method-call(java.lang.StringBuffer java.lang.StringBuffer.append(java.lang.String))
    | |             INVOKEVIRTUAL java.lang.StringBuffer.append (Ljava/lang/String;)Ljava/lang/StringBuffer;
    | method-call(java.lang.StringBuffer java.lang.StringBuffer.append(java.lang.String))
    |               POP
    |               GOTO L0
    |           L1: ALOAD_2     // Ljava/lang/StringBuffer; result   (line 294)
    | method-call(java.lang.String java.lang.StringBuffer.toString())
    | |             INVOKEVIRTUAL java.lang.StringBuffer.toString ()Ljava/lang/String;
    | method-call(java.lang.String java.lang.StringBuffer.toString())
    |               ARETURN
    method-execution(java.lang.String org.argouml.uml.util.namespace.StringNamespace.toString(java.lang.String))
  end public String toString(String)

  public String toString():
    method-execution(java.lang.String org.argouml.uml.util.namespace.StringNamespace.toString())
    |               ALOAD_0     // Lorg/argouml/uml/util/namespace/StringNamespace; this   (line 303)
    |               ALOAD_0     // Lorg/argouml/uml/util/namespace/StringNamespace; this
    |               GETFIELD org.argouml.uml.util.namespace.StringNamespace.token Ljava/lang/String;
    | method-call(java.lang.String org.argouml.uml.util.namespace.StringNamespace.toString(java.lang.String))
    | |             INVOKEVIRTUAL org.argouml.uml.util.namespace.StringNamespace.toString (Ljava/lang/String;)Ljava/lang/String;
    | method-call(java.lang.String org.argouml.uml.util.namespace.StringNamespace.toString(java.lang.String))
    |               ARETURN
    method-execution(java.lang.String org.argouml.uml.util.namespace.StringNamespace.toString())
  end public String toString()

  static void <clinit>():
    staticinitialization(void org.argouml.uml.util.namespace.StringNamespace.<clinit>())
    |               LDC_W org.argouml.uml.util.namespace.StringNamespace   (line 55)
    | method-call(java.lang.String java.lang.Class.getName())
    | |             INVOKEVIRTUAL java.lang.Class.getName ()Ljava/lang/String;
    | method-call(java.lang.String java.lang.Class.getName())
    | method-call(java.util.logging.Logger java.util.logging.Logger.getLogger(java.lang.String))
    | |             INVOKESTATIC java.util.logging.Logger.getLogger (Ljava/lang/String;)Ljava/util/logging/Logger;
    | method-call(java.util.logging.Logger java.util.logging.Logger.getLogger(java.lang.String))
    |               PUTSTATIC org.argouml.uml.util.namespace.StringNamespace.LOG Ljava/util/logging/Logger;
    |               RETURN
    staticinitialization(void org.argouml.uml.util.namespace.StringNamespace.<clinit>())
  end static void <clinit>()

  static final void pushNamespaceElement_aroundBody0(org.argouml.uml.util.namespace.StringNamespace, org.argouml.uml.util.namespace.StringNamespace, org.argouml.uml.util.namespace.NamespaceElement, org.aspectj.lang.JoinPoint):
                    ALOAD_1
                    ALOAD_2
                    INVOKEVIRTUAL org.argouml.uml.util.namespace.StringNamespace.pushNamespaceElement (Lorg/argouml/uml/util/namespace/NamespaceElement;)V   (line 102)
                    RETURN
  end static final void pushNamespaceElement_aroundBody0(org.argouml.uml.util.namespace.StringNamespace, org.argouml.uml.util.namespace.StringNamespace, org.argouml.uml.util.namespace.NamespaceElement, org.aspectj.lang.JoinPoint)

  static final void pushNamespaceElement_aroundBody2(org.argouml.uml.util.namespace.StringNamespace, org.argouml.uml.util.namespace.StringNamespace, org.argouml.uml.util.namespace.NamespaceElement, org.aspectj.lang.JoinPoint):
                    INVOKESTATIC kieker.monitoring.probe.aspectj.flow.operationCallObject.FullInstrumentation.aspectOf ()Lkieker/monitoring/probe/aspectj/flow/operationCallObject/FullInstrumentation;
                    ALOAD_0
                    ALOAD_1
                    ICONST_4
                    ANEWARRAY java.lang.Object
                    ASTORE 4
                    ALOAD 4
                    ICONST_0
                    ALOAD_0
                    AASTORE
                    ALOAD 4
                    ICONST_1
                    ALOAD_1
                    AASTORE
                    ALOAD 4
                    ICONST_2
                    ALOAD_2
                    AASTORE
                    ALOAD 4
                    ICONST_3
                    ALOAD_3
                    AASTORE
                    NEW org.argouml.uml.util.namespace.StringNamespace$AjcClosure1
                    DUP
                    ALOAD 4
                    INVOKESPECIAL org.argouml.uml.util.namespace.StringNamespace$AjcClosure1.<init> ([Ljava/lang/Object;)V
                    SIPUSH 4369
                    INVOKEVIRTUAL org.aspectj.runtime.internal.AroundClosure.linkClosureAndJoinPoint (I)Lorg/aspectj/lang/ProceedingJoinPoint;
                    GETSTATIC org.argouml.uml.util.namespace.StringNamespace.ajc$tjp_0 Lorg/aspectj/lang/JoinPoint$EnclosingStaticPart;
                    INVOKEVIRTUAL kieker.monitoring.probe.aspectj.flow.operationCallObject.AbstractAspect.member2memberOperation (Ljava/lang/Object;Ljava/lang/Object;Lorg/aspectj/lang/ProceedingJoinPoint;Lorg/aspectj/lang/JoinPoint$EnclosingStaticPart;)Ljava/lang/Object;
                    POP
                    RETURN
  end static final void pushNamespaceElement_aroundBody2(org.argouml.uml.util.namespace.StringNamespace, org.argouml.uml.util.namespace.StringNamespace, org.argouml.uml.util.namespace.NamespaceElement, org.aspectj.lang.JoinPoint)

  static final String toString_aroundBody4(org.argouml.uml.util.namespace.StringNamespace, Object, org.aspectj.lang.JoinPoint):
                    ALOAD_1
                    INVOKEVIRTUAL java.lang.Object.toString ()Ljava/lang/String;   (line 118)
                    ARETURN
  end static final String toString_aroundBody4(org.argouml.uml.util.namespace.StringNamespace, Object, org.aspectj.lang.JoinPoint)

  static final String toString_aroundBody6(org.argouml.uml.util.namespace.StringNamespace, Object, org.aspectj.lang.JoinPoint):
                    INVOKESTATIC kieker.monitoring.probe.aspectj.flow.operationCallObject.FullInstrumentation.aspectOf ()Lkieker/monitoring/probe/aspectj/flow/operationCallObject/FullInstrumentation;
                    ALOAD_0
                    ALOAD_1
                    ICONST_3
                    ANEWARRAY java.lang.Object
                    ASTORE_3
                    ALOAD_3
                    ICONST_0
                    ALOAD_0
                    AASTORE
                    ALOAD_3
                    ICONST_1
                    ALOAD_1
                    AASTORE
                    ALOAD_3
                    ICONST_2
                    ALOAD_2
                    AASTORE
                    NEW org.argouml.uml.util.namespace.StringNamespace$AjcClosure5
                    DUP
                    ALOAD_3
                    INVOKESPECIAL org.argouml.uml.util.namespace.StringNamespace$AjcClosure5.<init> ([Ljava/lang/Object;)V
                    SIPUSH 4369
                    INVOKEVIRTUAL org.aspectj.runtime.internal.AroundClosure.linkClosureAndJoinPoint (I)Lorg/aspectj/lang/ProceedingJoinPoint;
                    GETSTATIC org.argouml.uml.util.namespace.StringNamespace.ajc$tjp_2 Lorg/aspectj/lang/JoinPoint$EnclosingStaticPart;
                    INVOKEVIRTUAL kieker.monitoring.probe.aspectj.flow.operationCallObject.AbstractAspect.member2memberOperation (Ljava/lang/Object;Ljava/lang/Object;Lorg/aspectj/lang/ProceedingJoinPoint;Lorg/aspectj/lang/JoinPoint$EnclosingStaticPart;)Ljava/lang/Object;
                    CHECKCAST java.lang.String
                    ARETURN
  end static final String toString_aroundBody6(org.argouml.uml.util.namespace.StringNamespace, Object, org.aspectj.lang.JoinPoint)

  static final void pushNamespaceElement_aroundBody8(org.argouml.uml.util.namespace.StringNamespace, org.argouml.uml.util.namespace.StringNamespace, org.argouml.uml.util.namespace.NamespaceElement, org.aspectj.lang.JoinPoint):
                    ALOAD_1
                    ALOAD_2
                    INVOKEVIRTUAL org.argouml.uml.util.namespace.StringNamespace.pushNamespaceElement (Lorg/argouml/uml/util/namespace/NamespaceElement;)V   (line 118)
                    RETURN
  end static final void pushNamespaceElement_aroundBody8(org.argouml.uml.util.namespace.StringNamespace, org.argouml.uml.util.namespace.StringNamespace, org.argouml.uml.util.namespace.NamespaceElement, org.aspectj.lang.JoinPoint)

  static final void pushNamespaceElement_aroundBody10(org.argouml.uml.util.namespace.StringNamespace, org.argouml.uml.util.namespace.StringNamespace, org.argouml.uml.util.namespace.NamespaceElement, org.aspectj.lang.JoinPoint):
                    INVOKESTATIC kieker.monitoring.probe.aspectj.flow.operationCallObject.FullInstrumentation.aspectOf ()Lkieker/monitoring/probe/aspectj/flow/operationCallObject/FullInstrumentation;
                    ALOAD_0
                    ALOAD_1
                    ICONST_4
                    ANEWARRAY java.lang.Object
                    ASTORE 4
                    ALOAD 4
                    ICONST_0
                    ALOAD_0
                    AASTORE
                    ALOAD 4
                    ICONST_1
                    ALOAD_1
                    AASTORE
                    ALOAD 4
                    ICONST_2
                    ALOAD_2
                    AASTORE
                    ALOAD 4
                    ICONST_3
                    ALOAD_3
                    AASTORE
                    NEW org.argouml.uml.util.namespace.StringNamespace$AjcClosure9
                    DUP
                    ALOAD 4
                    INVOKESPECIAL org.argouml.uml.util.namespace.StringNamespace$AjcClosure9.<init> ([Ljava/lang/Object;)V
                    SIPUSH 4369
                    INVOKEVIRTUAL org.aspectj.runtime.internal.AroundClosure.linkClosureAndJoinPoint (I)Lorg/aspectj/lang/ProceedingJoinPoint;
                    GETSTATIC org.argouml.uml.util.namespace.StringNamespace.ajc$tjp_2 Lorg/aspectj/lang/JoinPoint$EnclosingStaticPart;
                    INVOKEVIRTUAL kieker.monitoring.probe.aspectj.flow.operationCallObject.AbstractAspect.member2memberOperation (Ljava/lang/Object;Ljava/lang/Object;Lorg/aspectj/lang/ProceedingJoinPoint;Lorg/aspectj/lang/JoinPoint$EnclosingStaticPart;)Ljava/lang/Object;
                    POP
                    RETURN
  end static final void pushNamespaceElement_aroundBody10(org.argouml.uml.util.namespace.StringNamespace, org.argouml.uml.util.namespace.StringNamespace, org.argouml.uml.util.namespace.NamespaceElement, org.aspectj.lang.JoinPoint)

  static final Object push_aroundBody12(org.argouml.uml.util.namespace.StringNamespace, java.util.Stack, Object, org.aspectj.lang.JoinPoint):
                    ALOAD_1
                    ALOAD_2
                    INVOKEVIRTUAL java.util.Stack.push (Ljava/lang/Object;)Ljava/lang/Object;   (line 137)
                    ARETURN
  end static final Object push_aroundBody12(org.argouml.uml.util.namespace.StringNamespace, java.util.Stack, Object, org.aspectj.lang.JoinPoint)

  static final Object push_aroundBody14(org.argouml.uml.util.namespace.StringNamespace, java.util.Stack, Object, org.aspectj.lang.JoinPoint):
                    INVOKESTATIC kieker.monitoring.probe.aspectj.flow.operationCallObject.FullInstrumentation.aspectOf ()Lkieker/monitoring/probe/aspectj/flow/operationCallObject/FullInstrumentation;
                    ALOAD_0
                    ALOAD_1
                    ICONST_4
                    ANEWARRAY java.lang.Object
                    ASTORE 4
                    ALOAD 4
                    ICONST_0
                    ALOAD_0
                    AASTORE
                    ALOAD 4
                    ICONST_1
                    ALOAD_1
                    AASTORE
                    ALOAD 4
                    ICONST_2
                    ALOAD_2
                    AASTORE
                    ALOAD 4
                    ICONST_3
                    ALOAD_3
                    AASTORE
                    NEW org.argouml.uml.util.namespace.StringNamespace$AjcClosure13
                    DUP
                    ALOAD 4
                    INVOKESPECIAL org.argouml.uml.util.namespace.StringNamespace$AjcClosure13.<init> ([Ljava/lang/Object;)V
                    SIPUSH 4369
                    INVOKEVIRTUAL org.aspectj.runtime.internal.AroundClosure.linkClosureAndJoinPoint (I)Lorg/aspectj/lang/ProceedingJoinPoint;
                    GETSTATIC org.argouml.uml.util.namespace.StringNamespace.ajc$tjp_5 Lorg/aspectj/lang/JoinPoint$EnclosingStaticPart;
                    INVOKEVIRTUAL kieker.monitoring.probe.aspectj.flow.operationCallObject.AbstractAspect.member2memberOperation (Ljava/lang/Object;Ljava/lang/Object;Lorg/aspectj/lang/ProceedingJoinPoint;Lorg/aspectj/lang/JoinPoint$EnclosingStaticPart;)Ljava/lang/Object;
                    ARETURN
  end static final Object push_aroundBody14(org.argouml.uml.util.namespace.StringNamespace, java.util.Stack, Object, org.aspectj.lang.JoinPoint)

  static final void pushNamespaceElement_aroundBody16(org.argouml.uml.util.namespace.StringNamespace, org.argouml.uml.util.namespace.NamespaceElement, org.aspectj.lang.JoinPoint):
                    ALOAD_0     // Lorg/argouml/uml/util/namespace/StringNamespace; ajc$this   (line 137)
                    GETFIELD org.argouml.uml.util.namespace.StringNamespace.ns Ljava/util/Stack;
                    ALOAD_1     // Lorg/argouml/uml/util/namespace/NamespaceElement; element
                    ASTORE_3
                    ASTORE 5
                    GETSTATIC org.argouml.uml.util.namespace.StringNamespace.ajc$tjp_6 Lorg/aspectj/lang/JoinPoint$StaticPart;
                    ALOAD_0
                    ALOAD 5
                    ALOAD_3
                    INVOKESTATIC org.aspectj.runtime.reflect.Factory.makeJP (Lorg/aspectj/lang/JoinPoint$StaticPart;Ljava/lang/Object;Ljava/lang/Object;Ljava/lang/Object;)Lorg/aspectj/lang/JoinPoint;
                    ASTORE 7
    method-call(java.lang.Object java.util.Stack.push(java.lang.Object))
    |               INVOKESTATIC kieker.monitoring.probe.aspectj.flow.operationCall.FullInstrumentation.aspectOf ()Lkieker/monitoring/probe/aspectj/flow/operationCall/FullInstrumentation;
    |               ALOAD_0
    |               ALOAD 5
    |               ICONST_4
    |               ANEWARRAY java.lang.Object
    |               ASTORE 9
    |               ALOAD 9
    |               ICONST_0
    |               ALOAD_0
    |               AASTORE
    |               ALOAD 9
    |               ICONST_1
    |               ALOAD 5
    |               AASTORE
    |               ALOAD 9
    |               ICONST_2
    |               ALOAD_3
    |               AASTORE
    |               ALOAD 9
    |               ICONST_3
    |               ALOAD 7
    |               AASTORE
    |               NEW org.argouml.uml.util.namespace.StringNamespace$AjcClosure15
    |               DUP
    |               ALOAD 9
    |               INVOKESPECIAL org.argouml.uml.util.namespace.StringNamespace$AjcClosure15.<init> ([Ljava/lang/Object;)V
    |               SIPUSH 4369
    |               INVOKEVIRTUAL org.aspectj.runtime.internal.AroundClosure.linkClosureAndJoinPoint (I)Lorg/aspectj/lang/ProceedingJoinPoint;
    |               GETSTATIC org.argouml.uml.util.namespace.StringNamespace.ajc$tjp_5 Lorg/aspectj/lang/JoinPoint$EnclosingStaticPart;
    |               INVOKEVIRTUAL kieker.monitoring.probe.aspectj.flow.operationCall.AbstractAspect.member2memberOperation (Ljava/lang/Object;Ljava/lang/Object;Lorg/aspectj/lang/ProceedingJoinPoint;Lorg/aspectj/lang/JoinPoint$EnclosingStaticPart;)Ljava/lang/Object;
    method-call(java.lang.Object java.util.Stack.push(java.lang.Object))
                    POP
                    RETURN   (line 138)
  end static final void pushNamespaceElement_aroundBody16(org.argouml.uml.util.namespace.StringNamespace, org.argouml.uml.util.namespace.NamespaceElement, org.aspectj.lang.JoinPoint)

  static final Object peek_aroundBody18(org.argouml.uml.util.namespace.StringNamespace, java.util.Stack, org.aspectj.lang.JoinPoint):
                    ALOAD_1
                    INVOKEVIRTUAL java.util.Stack.peek ()Ljava/lang/Object;   (line 144)
                    ARETURN
  end static final Object peek_aroundBody18(org.argouml.uml.util.namespace.StringNamespace, java.util.Stack, org.aspectj.lang.JoinPoint)

  static final Object peek_aroundBody20(org.argouml.uml.util.namespace.StringNamespace, java.util.Stack, org.aspectj.lang.JoinPoint):
                    INVOKESTATIC kieker.monitoring.probe.aspectj.flow.operationCallObject.FullInstrumentation.aspectOf ()Lkieker/monitoring/probe/aspectj/flow/operationCallObject/FullInstrumentation;
                    ALOAD_0
                    ALOAD_1
                    ICONST_3
                    ANEWARRAY java.lang.Object
                    ASTORE_3
                    ALOAD_3
                    ICONST_0
                    ALOAD_0
                    AASTORE
                    ALOAD_3
                    ICONST_1
                    ALOAD_1
                    AASTORE
                    ALOAD_3
                    ICONST_2
                    ALOAD_2
                    AASTORE
                    NEW org.argouml.uml.util.namespace.StringNamespace$AjcClosure19
                    DUP
                    ALOAD_3
                    INVOKESPECIAL org.argouml.uml.util.namespace.StringNamespace$AjcClosure19.<init> ([Ljava/lang/Object;)V
                    SIPUSH 4369
                    INVOKEVIRTUAL org.aspectj.runtime.internal.AroundClosure.linkClosureAndJoinPoint (I)Lorg/aspectj/lang/ProceedingJoinPoint;
                    GETSTATIC org.argouml.uml.util.namespace.StringNamespace.ajc$tjp_7 Lorg/aspectj/lang/JoinPoint$EnclosingStaticPart;
                    INVOKEVIRTUAL kieker.monitoring.probe.aspectj.flow.operationCallObject.AbstractAspect.member2memberOperation (Ljava/lang/Object;Ljava/lang/Object;Lorg/aspectj/lang/ProceedingJoinPoint;Lorg/aspectj/lang/JoinPoint$EnclosingStaticPart;)Ljava/lang/Object;
                    ARETURN
  end static final Object peek_aroundBody20(org.argouml.uml.util.namespace.StringNamespace, java.util.Stack, org.aspectj.lang.JoinPoint)

  static final org.argouml.uml.util.namespace.NamespaceElement peekNamespaceElement_aroundBody22(org.argouml.uml.util.namespace.StringNamespace, org.aspectj.lang.JoinPoint):
                    ALOAD_0     // Lorg/argouml/uml/util/namespace/StringNamespace; ajc$this   (line 144)
                    GETFIELD org.argouml.uml.util.namespace.StringNamespace.ns Ljava/util/Stack;
                    ASTORE_2
                    GETSTATIC org.argouml.uml.util.namespace.StringNamespace.ajc$tjp_8 Lorg/aspectj/lang/JoinPoint$StaticPart;
                    ALOAD_0
                    ALOAD_2
                    INVOKESTATIC org.aspectj.runtime.reflect.Factory.makeJP (Lorg/aspectj/lang/JoinPoint$StaticPart;Ljava/lang/Object;Ljava/lang/Object;)Lorg/aspectj/lang/JoinPoint;
                    ASTORE 4
    method-call(java.lang.Object java.util.Stack.peek())
    |               INVOKESTATIC kieker.monitoring.probe.aspectj.flow.operationCall.FullInstrumentation.aspectOf ()Lkieker/monitoring/probe/aspectj/flow/operationCall/FullInstrumentation;
    |               ALOAD_0
    |               ALOAD_2
    |               ICONST_3
    |               ANEWARRAY java.lang.Object
    |               ASTORE 6
    |               ALOAD 6
    |               ICONST_0
    |               ALOAD_0
    |               AASTORE
    |               ALOAD 6
    |               ICONST_1
    |               ALOAD_2
    |               AASTORE
    |               ALOAD 6
    |               ICONST_2
    |               ALOAD 4
    |               AASTORE
    |               NEW org.argouml.uml.util.namespace.StringNamespace$AjcClosure21
    |               DUP
    |               ALOAD 6
    |               INVOKESPECIAL org.argouml.uml.util.namespace.StringNamespace$AjcClosure21.<init> ([Ljava/lang/Object;)V
    |               SIPUSH 4369
    |               INVOKEVIRTUAL org.aspectj.runtime.internal.AroundClosure.linkClosureAndJoinPoint (I)Lorg/aspectj/lang/ProceedingJoinPoint;
    |               GETSTATIC org.argouml.uml.util.namespace.StringNamespace.ajc$tjp_7 Lorg/aspectj/lang/JoinPoint$EnclosingStaticPart;
    |               INVOKEVIRTUAL kieker.monitoring.probe.aspectj.flow.operationCall.AbstractAspect.member2memberOperation (Ljava/lang/Object;Ljava/lang/Object;Lorg/aspectj/lang/ProceedingJoinPoint;Lorg/aspectj/lang/JoinPoint$EnclosingStaticPart;)Ljava/lang/Object;
    method-call(java.lang.Object java.util.Stack.peek())
                    CHECKCAST org.argouml.uml.util.namespace.NamespaceElement
                    ARETURN
  end static final org.argouml.uml.util.namespace.NamespaceElement peekNamespaceElement_aroundBody22(org.argouml.uml.util.namespace.StringNamespace, org.aspectj.lang.JoinPoint)

  static final Object push_aroundBody24(org.argouml.uml.util.namespace.StringNamespace, java.util.Stack, Object, org.aspectj.lang.JoinPoint):
                    ALOAD_1
                    ALOAD_2
                    INVOKEVIRTUAL java.util.Stack.push (Ljava/lang/Object;)Ljava/lang/Object;   (line 154)
                    ARETURN
  end static final Object push_aroundBody24(org.argouml.uml.util.namespace.StringNamespace, java.util.Stack, Object, org.aspectj.lang.JoinPoint)

  static final Object push_aroundBody26(org.argouml.uml.util.namespace.StringNamespace, java.util.Stack, Object, org.aspectj.lang.JoinPoint):
                    INVOKESTATIC kieker.monitoring.probe.aspectj.flow.operationCallObject.FullInstrumentation.aspectOf ()Lkieker/monitoring/probe/aspectj/flow/operationCallObject/FullInstrumentation;
                    ALOAD_0
                    ALOAD_1
                    ICONST_4
                    ANEWARRAY java.lang.Object
                    ASTORE 4
                    ALOAD 4
                    ICONST_0
                    ALOAD_0
                    AASTORE
                    ALOAD 4
                    ICONST_1
                    ALOAD_1
                    AASTORE
                    ALOAD 4
                    ICONST_2
                    ALOAD_2
                    AASTORE
                    ALOAD 4
                    ICONST_3
                    ALOAD_3
                    AASTORE
                    NEW org.argouml.uml.util.namespace.StringNamespace$AjcClosure25
                    DUP
                    ALOAD 4
                    INVOKESPECIAL org.argouml.uml.util.namespace.StringNamespace$AjcClosure25.<init> ([Ljava/lang/Object;)V
                    SIPUSH 4369
                    INVOKEVIRTUAL org.aspectj.runtime.internal.AroundClosure.linkClosureAndJoinPoint (I)Lorg/aspectj/lang/ProceedingJoinPoint;
                    GETSTATIC org.argouml.uml.util.namespace.StringNamespace.ajc$tjp_9 Lorg/aspectj/lang/JoinPoint$EnclosingStaticPart;
                    INVOKEVIRTUAL kieker.monitoring.probe.aspectj.flow.operationCallObject.AbstractAspect.member2memberOperation (Ljava/lang/Object;Ljava/lang/Object;Lorg/aspectj/lang/ProceedingJoinPoint;Lorg/aspectj/lang/JoinPoint$EnclosingStaticPart;)Ljava/lang/Object;
                    ARETURN
  end static final Object push_aroundBody26(org.argouml.uml.util.namespace.StringNamespace, java.util.Stack, Object, org.aspectj.lang.JoinPoint)

  static final void pushNamespaceElement_aroundBody28(org.argouml.uml.util.namespace.StringNamespace, String, org.aspectj.lang.JoinPoint):
                    ALOAD_0     // Lorg/argouml/uml/util/namespace/StringNamespace; ajc$this   (line 154)
                    GETFIELD org.argouml.uml.util.namespace.StringNamespace.ns Ljava/util/Stack;
                    NEW org.argouml.uml.util.namespace.StringNamespaceElement
                    DUP
                    ALOAD_1     // Ljava/lang/String; element
                    INVOKESPECIAL org.argouml.uml.util.namespace.StringNamespaceElement.<init> (Ljava/lang/String;)V
                    ASTORE_3
                    ASTORE 5
                    GETSTATIC org.argouml.uml.util.namespace.StringNamespace.ajc$tjp_10 Lorg/aspectj/lang/JoinPoint$StaticPart;
                    ALOAD_0
                    ALOAD 5
                    ALOAD_3
                    INVOKESTATIC org.aspectj.runtime.reflect.Factory.makeJP (Lorg/aspectj/lang/JoinPoint$StaticPart;Ljava/lang/Object;Ljava/lang/Object;Ljava/lang/Object;)Lorg/aspectj/lang/JoinPoint;
                    ASTORE 7
    method-call(java.lang.Object java.util.Stack.push(java.lang.Object))
    |               INVOKESTATIC kieker.monitoring.probe.aspectj.flow.operationCall.FullInstrumentation.aspectOf ()Lkieker/monitoring/probe/aspectj/flow/operationCall/FullInstrumentation;
    |               ALOAD_0
    |               ALOAD 5
    |               ICONST_4
    |               ANEWARRAY java.lang.Object
    |               ASTORE 9
    |               ALOAD 9
    |               ICONST_0
    |               ALOAD_0
    |               AASTORE
    |               ALOAD 9
    |               ICONST_1
    |               ALOAD 5
    |               AASTORE
    |               ALOAD 9
    |               ICONST_2
    |               ALOAD_3
    |               AASTORE
    |               ALOAD 9
    |               ICONST_3
    |               ALOAD 7
    |               AASTORE
    |               NEW org.argouml.uml.util.namespace.StringNamespace$AjcClosure27
    |               DUP
    |               ALOAD 9
    |               INVOKESPECIAL org.argouml.uml.util.namespace.StringNamespace$AjcClosure27.<init> ([Ljava/lang/Object;)V
    |               SIPUSH 4369
    |               INVOKEVIRTUAL org.aspectj.runtime.internal.AroundClosure.linkClosureAndJoinPoint (I)Lorg/aspectj/lang/ProceedingJoinPoint;
    |               GETSTATIC org.argouml.uml.util.namespace.StringNamespace.ajc$tjp_9 Lorg/aspectj/lang/JoinPoint$EnclosingStaticPart;
    |               INVOKEVIRTUAL kieker.monitoring.probe.aspectj.flow.operationCall.AbstractAspect.member2memberOperation (Ljava/lang/Object;Ljava/lang/Object;Lorg/aspectj/lang/ProceedingJoinPoint;Lorg/aspectj/lang/JoinPoint$EnclosingStaticPart;)Ljava/lang/Object;
    method-call(java.lang.Object java.util.Stack.push(java.lang.Object))
                    POP
                    RETURN   (line 155)
  end static final void pushNamespaceElement_aroundBody28(org.argouml.uml.util.namespace.StringNamespace, String, org.aspectj.lang.JoinPoint)

  static final Object pop_aroundBody30(org.argouml.uml.util.namespace.StringNamespace, java.util.Stack, org.aspectj.lang.JoinPoint):
                    ALOAD_1
                    INVOKEVIRTUAL java.util.Stack.pop ()Ljava/lang/Object;   (line 161)
                    ARETURN
  end static final Object pop_aroundBody30(org.argouml.uml.util.namespace.StringNamespace, java.util.Stack, org.aspectj.lang.JoinPoint)

  static final Object pop_aroundBody32(org.argouml.uml.util.namespace.StringNamespace, java.util.Stack, org.aspectj.lang.JoinPoint):
                    INVOKESTATIC kieker.monitoring.probe.aspectj.flow.operationCallObject.FullInstrumentation.aspectOf ()Lkieker/monitoring/probe/aspectj/flow/operationCallObject/FullInstrumentation;
                    ALOAD_0
                    ALOAD_1
                    ICONST_3
                    ANEWARRAY java.lang.Object
                    ASTORE_3
                    ALOAD_3
                    ICONST_0
                    ALOAD_0
                    AASTORE
                    ALOAD_3
                    ICONST_1
                    ALOAD_1
                    AASTORE
                    ALOAD_3
                    ICONST_2
                    ALOAD_2
                    AASTORE
                    NEW org.argouml.uml.util.namespace.StringNamespace$AjcClosure31
                    DUP
                    ALOAD_3
                    INVOKESPECIAL org.argouml.uml.util.namespace.StringNamespace$AjcClosure31.<init> ([Ljava/lang/Object;)V
                    SIPUSH 4369
                    INVOKEVIRTUAL org.aspectj.runtime.internal.AroundClosure.linkClosureAndJoinPoint (I)Lorg/aspectj/lang/ProceedingJoinPoint;
                    GETSTATIC org.argouml.uml.util.namespace.StringNamespace.ajc$tjp_11 Lorg/aspectj/lang/JoinPoint$EnclosingStaticPart;
                    INVOKEVIRTUAL kieker.monitoring.probe.aspectj.flow.operationCallObject.AbstractAspect.member2memberOperation (Ljava/lang/Object;Ljava/lang/Object;Lorg/aspectj/lang/ProceedingJoinPoint;Lorg/aspectj/lang/JoinPoint$EnclosingStaticPart;)Ljava/lang/Object;
                    ARETURN
  end static final Object pop_aroundBody32(org.argouml.uml.util.namespace.StringNamespace, java.util.Stack, org.aspectj.lang.JoinPoint)

  static final org.argouml.uml.util.namespace.NamespaceElement popNamespaceElement_aroundBody34(org.argouml.uml.util.namespace.StringNamespace, org.aspectj.lang.JoinPoint):
                    ALOAD_0     // Lorg/argouml/uml/util/namespace/StringNamespace; ajc$this   (line 161)
                    GETFIELD org.argouml.uml.util.namespace.StringNamespace.ns Ljava/util/Stack;
                    ASTORE_2
                    GETSTATIC org.argouml.uml.util.namespace.StringNamespace.ajc$tjp_12 Lorg/aspectj/lang/JoinPoint$StaticPart;
                    ALOAD_0
                    ALOAD_2
                    INVOKESTATIC org.aspectj.runtime.reflect.Factory.makeJP (Lorg/aspectj/lang/JoinPoint$StaticPart;Ljava/lang/Object;Ljava/lang/Object;)Lorg/aspectj/lang/JoinPoint;
                    ASTORE 4
    method-call(java.lang.Object java.util.Stack.pop())
    |               INVOKESTATIC kieker.monitoring.probe.aspectj.flow.operationCall.FullInstrumentation.aspectOf ()Lkieker/monitoring/probe/aspectj/flow/operationCall/FullInstrumentation;
    |               ALOAD_0
    |               ALOAD_2
    |               ICONST_3
    |               ANEWARRAY java.lang.Object
    |               ASTORE 6
    |               ALOAD 6
    |               ICONST_0
    |               ALOAD_0
    |               AASTORE
    |               ALOAD 6
    |               ICONST_1
    |               ALOAD_2
    |               AASTORE
    |               ALOAD 6
    |               ICONST_2
    |               ALOAD 4
    |               AASTORE
    |               NEW org.argouml.uml.util.namespace.StringNamespace$AjcClosure33
    |               DUP
    |               ALOAD 6
    |               INVOKESPECIAL org.argouml.uml.util.namespace.StringNamespace$AjcClosure33.<init> ([Ljava/lang/Object;)V
    |               SIPUSH 4369
    |               INVOKEVIRTUAL org.aspectj.runtime.internal.AroundClosure.linkClosureAndJoinPoint (I)Lorg/aspectj/lang/ProceedingJoinPoint;
    |               GETSTATIC org.argouml.uml.util.namespace.StringNamespace.ajc$tjp_11 Lorg/aspectj/lang/JoinPoint$EnclosingStaticPart;
    |               INVOKEVIRTUAL kieker.monitoring.probe.aspectj.flow.operationCall.AbstractAspect.member2memberOperation (Ljava/lang/Object;Ljava/lang/Object;Lorg/aspectj/lang/ProceedingJoinPoint;Lorg/aspectj/lang/JoinPoint$EnclosingStaticPart;)Ljava/lang/Object;
    method-call(java.lang.Object java.util.Stack.pop())
                    CHECKCAST org.argouml.uml.util.namespace.NamespaceElement
                    ARETURN
  end static final org.argouml.uml.util.namespace.NamespaceElement popNamespaceElement_aroundBody34(org.argouml.uml.util.namespace.StringNamespace, org.aspectj.lang.JoinPoint)
end public class org.argouml.uml.util.namespace.StringNamespace

public class org.argouml.uml.util.namespace.StringNamespace$AjcClosure1 extends org.aspectj.runtime.internal.AroundClosure:
  public void <init>(Object[]):
                    ALOAD_0
                    ALOAD_1
                    INVOKESPECIAL org.aspectj.runtime.internal.AroundClosure.<init> ([Ljava/lang/Object;)V
                    RETURN
  end public void <init>(Object[])

  public Object run(Object[]):
                    ALOAD_0
                    GETFIELD org.aspectj.runtime.internal.AroundClosure.state [Ljava/lang/Object;
                    ASTORE_2
                    ALOAD_2
                    ICONST_0
                    AALOAD
                    CHECKCAST org.argouml.uml.util.namespace.StringNamespace
                    ALOAD_2
                    ICONST_1
                    AALOAD
                    CHECKCAST org.argouml.uml.util.namespace.StringNamespace
                    ALOAD_2
                    ICONST_2
                    AALOAD
                    CHECKCAST org.argouml.uml.util.namespace.NamespaceElement
                    ALOAD_2
                    ICONST_3
                    AALOAD
                    CHECKCAST org.aspectj.lang.JoinPoint
                    INVOKESTATIC org.argouml.uml.util.namespace.StringNamespace.pushNamespaceElement_aroundBody0 (Lorg/argouml/uml/util/namespace/StringNamespace;Lorg/argouml/uml/util/namespace/StringNamespace;Lorg/argouml/uml/util/namespace/NamespaceElement;Lorg/aspectj/lang/JoinPoint;)V
                    ACONST_NULL
                    ARETURN
  end public Object run(Object[])
end public class org.argouml.uml.util.namespace.StringNamespace$AjcClosure1

public class org.argouml.uml.util.namespace.StringNamespace$AjcClosure3 extends org.aspectj.runtime.internal.AroundClosure:
  public void <init>(Object[]):
                    ALOAD_0
                    ALOAD_1
                    INVOKESPECIAL org.aspectj.runtime.internal.AroundClosure.<init> ([Ljava/lang/Object;)V
                    RETURN
  end public void <init>(Object[])

  public Object run(Object[]):
                    ALOAD_0
                    GETFIELD org.aspectj.runtime.internal.AroundClosure.state [Ljava/lang/Object;
                    ASTORE_2
                    ALOAD_2
                    ICONST_0
                    AALOAD
                    CHECKCAST org.argouml.uml.util.namespace.StringNamespace
                    ALOAD_2
                    ICONST_1
                    AALOAD
                    CHECKCAST org.argouml.uml.util.namespace.StringNamespace
                    ALOAD_2
                    ICONST_2
                    AALOAD
                    CHECKCAST org.argouml.uml.util.namespace.NamespaceElement
                    ALOAD_2
                    ICONST_3
                    AALOAD
                    CHECKCAST org.aspectj.lang.JoinPoint
                    INVOKESTATIC org.argouml.uml.util.namespace.StringNamespace.pushNamespaceElement_aroundBody2 (Lorg/argouml/uml/util/namespace/StringNamespace;Lorg/argouml/uml/util/namespace/StringNamespace;Lorg/argouml/uml/util/namespace/NamespaceElement;Lorg/aspectj/lang/JoinPoint;)V
                    ACONST_NULL
                    ARETURN
  end public Object run(Object[])
end public class org.argouml.uml.util.namespace.StringNamespace$AjcClosure3

public class org.argouml.uml.util.namespace.StringNamespace$AjcClosure5 extends org.aspectj.runtime.internal.AroundClosure:
  public void <init>(Object[]):
                    ALOAD_0
                    ALOAD_1
                    INVOKESPECIAL org.aspectj.runtime.internal.AroundClosure.<init> ([Ljava/lang/Object;)V
                    RETURN
  end public void <init>(Object[])

  public Object run(Object[]):
                    ALOAD_0
                    GETFIELD org.aspectj.runtime.internal.AroundClosure.state [Ljava/lang/Object;
                    ASTORE_2
                    ALOAD_2
                    ICONST_0
                    AALOAD
                    CHECKCAST org.argouml.uml.util.namespace.StringNamespace
                    ALOAD_2
                    ICONST_1
                    AALOAD
                    ALOAD_2
                    ICONST_2
                    AALOAD
                    CHECKCAST org.aspectj.lang.JoinPoint
                    INVOKESTATIC org.argouml.uml.util.namespace.StringNamespace.toString_aroundBody4 (Lorg/argouml/uml/util/namespace/StringNamespace;Ljava/lang/Object;Lorg/aspectj/lang/JoinPoint;)Ljava/lang/String;
                    ARETURN
  end public Object run(Object[])
end public class org.argouml.uml.util.namespace.StringNamespace$AjcClosure5

public class org.argouml.uml.util.namespace.StringNamespace$AjcClosure7 extends org.aspectj.runtime.internal.AroundClosure:
  public void <init>(Object[]):
                    ALOAD_0
                    ALOAD_1
                    INVOKESPECIAL org.aspectj.runtime.internal.AroundClosure.<init> ([Ljava/lang/Object;)V
                    RETURN
  end public void <init>(Object[])

  public Object run(Object[]):
                    ALOAD_0
                    GETFIELD org.aspectj.runtime.internal.AroundClosure.state [Ljava/lang/Object;
                    ASTORE_2
                    ALOAD_2
                    ICONST_0
                    AALOAD
                    CHECKCAST org.argouml.uml.util.namespace.StringNamespace
                    ALOAD_2
                    ICONST_1
                    AALOAD
                    ALOAD_2
                    ICONST_2
                    AALOAD
                    CHECKCAST org.aspectj.lang.JoinPoint
                    INVOKESTATIC org.argouml.uml.util.namespace.StringNamespace.toString_aroundBody6 (Lorg/argouml/uml/util/namespace/StringNamespace;Ljava/lang/Object;Lorg/aspectj/lang/JoinPoint;)Ljava/lang/String;
                    ARETURN
  end public Object run(Object[])
end public class org.argouml.uml.util.namespace.StringNamespace$AjcClosure7

public class org.argouml.uml.util.namespace.StringNamespace$AjcClosure9 extends org.aspectj.runtime.internal.AroundClosure:
  public void <init>(Object[]):
                    ALOAD_0
                    ALOAD_1
                    INVOKESPECIAL org.aspectj.runtime.internal.AroundClosure.<init> ([Ljava/lang/Object;)V
                    RETURN
  end public void <init>(Object[])

  public Object run(Object[]):
                    ALOAD_0
                    GETFIELD org.aspectj.runtime.internal.AroundClosure.state [Ljava/lang/Object;
                    ASTORE_2
                    ALOAD_2
                    ICONST_0
                    AALOAD
                    CHECKCAST org.argouml.uml.util.namespace.StringNamespace
                    ALOAD_2
                    ICONST_1
                    AALOAD
                    CHECKCAST org.argouml.uml.util.namespace.StringNamespace
                    ALOAD_2
                    ICONST_2
                    AALOAD
                    CHECKCAST org.argouml.uml.util.namespace.NamespaceElement
                    ALOAD_2
                    ICONST_3
                    AALOAD
                    CHECKCAST org.aspectj.lang.JoinPoint
                    INVOKESTATIC org.argouml.uml.util.namespace.StringNamespace.pushNamespaceElement_aroundBody8 (Lorg/argouml/uml/util/namespace/StringNamespace;Lorg/argouml/uml/util/namespace/StringNamespace;Lorg/argouml/uml/util/namespace/NamespaceElement;Lorg/aspectj/lang/JoinPoint;)V
                    ACONST_NULL
                    ARETURN
  end public Object run(Object[])
end public class org.argouml.uml.util.namespace.StringNamespace$AjcClosure9

public class org.argouml.uml.util.namespace.StringNamespace$AjcClosure11 extends org.aspectj.runtime.internal.AroundClosure:
  public void <init>(Object[]):
                    ALOAD_0
                    ALOAD_1
                    INVOKESPECIAL org.aspectj.runtime.internal.AroundClosure.<init> ([Ljava/lang/Object;)V
                    RETURN
  end public void <init>(Object[])

  public Object run(Object[]):
                    ALOAD_0
                    GETFIELD org.aspectj.runtime.internal.AroundClosure.state [Ljava/lang/Object;
                    ASTORE_2
                    ALOAD_2
                    ICONST_0
                    AALOAD
                    CHECKCAST org.argouml.uml.util.namespace.StringNamespace
                    ALOAD_2
                    ICONST_1
                    AALOAD
                    CHECKCAST org.argouml.uml.util.namespace.StringNamespace
                    ALOAD_2
                    ICONST_2
                    AALOAD
                    CHECKCAST org.argouml.uml.util.namespace.NamespaceElement
                    ALOAD_2
                    ICONST_3
                    AALOAD
                    CHECKCAST org.aspectj.lang.JoinPoint
                    INVOKESTATIC org.argouml.uml.util.namespace.StringNamespace.pushNamespaceElement_aroundBody10 (Lorg/argouml/uml/util/namespace/StringNamespace;Lorg/argouml/uml/util/namespace/StringNamespace;Lorg/argouml/uml/util/namespace/NamespaceElement;Lorg/aspectj/lang/JoinPoint;)V
                    ACONST_NULL
                    ARETURN
  end public Object run(Object[])
end public class org.argouml.uml.util.namespace.StringNamespace$AjcClosure11

public class org.argouml.uml.util.namespace.StringNamespace$AjcClosure13 extends org.aspectj.runtime.internal.AroundClosure:
  public void <init>(Object[]):
                    ALOAD_0
                    ALOAD_1
                    INVOKESPECIAL org.aspectj.runtime.internal.AroundClosure.<init> ([Ljava/lang/Object;)V
                    RETURN
  end public void <init>(Object[])

  public Object run(Object[]):
                    ALOAD_0
                    GETFIELD org.aspectj.runtime.internal.AroundClosure.state [Ljava/lang/Object;
                    ASTORE_2
                    ALOAD_2
                    ICONST_0
                    AALOAD
                    CHECKCAST org.argouml.uml.util.namespace.StringNamespace
                    ALOAD_2
                    ICONST_1
                    AALOAD
                    CHECKCAST java.util.Stack
                    ALOAD_2
                    ICONST_2
                    AALOAD
                    ALOAD_2
                    ICONST_3
                    AALOAD
                    CHECKCAST org.aspectj.lang.JoinPoint
                    INVOKESTATIC org.argouml.uml.util.namespace.StringNamespace.push_aroundBody12 (Lorg/argouml/uml/util/namespace/StringNamespace;Ljava/util/Stack;Ljava/lang/Object;Lorg/aspectj/lang/JoinPoint;)Ljava/lang/Object;
                    ARETURN
  end public Object run(Object[])
end public class org.argouml.uml.util.namespace.StringNamespace$AjcClosure13

public class org.argouml.uml.util.namespace.StringNamespace$AjcClosure15 extends org.aspectj.runtime.internal.AroundClosure:
  public void <init>(Object[]):
                    ALOAD_0
                    ALOAD_1
                    INVOKESPECIAL org.aspectj.runtime.internal.AroundClosure.<init> ([Ljava/lang/Object;)V
                    RETURN
  end public void <init>(Object[])

  public Object run(Object[]):
                    ALOAD_0
                    GETFIELD org.aspectj.runtime.internal.AroundClosure.state [Ljava/lang/Object;
                    ASTORE_2
                    ALOAD_2
                    ICONST_0
                    AALOAD
                    CHECKCAST org.argouml.uml.util.namespace.StringNamespace
                    ALOAD_2
                    ICONST_1
                    AALOAD
                    CHECKCAST java.util.Stack
                    ALOAD_2
                    ICONST_2
                    AALOAD
                    ALOAD_2
                    ICONST_3
                    AALOAD
                    CHECKCAST org.aspectj.lang.JoinPoint
                    INVOKESTATIC org.argouml.uml.util.namespace.StringNamespace.push_aroundBody14 (Lorg/argouml/uml/util/namespace/StringNamespace;Ljava/util/Stack;Ljava/lang/Object;Lorg/aspectj/lang/JoinPoint;)Ljava/lang/Object;
                    ARETURN
  end public Object run(Object[])
end public class org.argouml.uml.util.namespace.StringNamespace$AjcClosure15

public class org.argouml.uml.util.namespace.StringNamespace$AjcClosure17 extends org.aspectj.runtime.internal.AroundClosure:
  public void <init>(Object[]):
                    ALOAD_0
                    ALOAD_1
                    INVOKESPECIAL org.aspectj.runtime.internal.AroundClosure.<init> ([Ljava/lang/Object;)V
                    RETURN
  end public void <init>(Object[])

  public Object run(Object[]):
                    ALOAD_0
                    GETFIELD org.aspectj.runtime.internal.AroundClosure.state [Ljava/lang/Object;
                    ASTORE_2
                    ALOAD_2
                    ICONST_0
                    AALOAD
                    CHECKCAST org.argouml.uml.util.namespace.StringNamespace
                    ALOAD_2
                    ICONST_1
                    AALOAD
                    CHECKCAST org.argouml.uml.util.namespace.NamespaceElement
                    ALOAD_2
                    ICONST_2
                    AALOAD
                    CHECKCAST org.aspectj.lang.JoinPoint
                    INVOKESTATIC org.argouml.uml.util.namespace.StringNamespace.pushNamespaceElement_aroundBody16 (Lorg/argouml/uml/util/namespace/StringNamespace;Lorg/argouml/uml/util/namespace/NamespaceElement;Lorg/aspectj/lang/JoinPoint;)V
                    ACONST_NULL
                    ARETURN
  end public Object run(Object[])
end public class org.argouml.uml.util.namespace.StringNamespace$AjcClosure17

public class org.argouml.uml.util.namespace.StringNamespace$AjcClosure19 extends org.aspectj.runtime.internal.AroundClosure:
  public void <init>(Object[]):
                    ALOAD_0
                    ALOAD_1
                    INVOKESPECIAL org.aspectj.runtime.internal.AroundClosure.<init> ([Ljava/lang/Object;)V
                    RETURN
  end public void <init>(Object[])

  public Object run(Object[]):
                    ALOAD_0
                    GETFIELD org.aspectj.runtime.internal.AroundClosure.state [Ljava/lang/Object;
                    ASTORE_2
                    ALOAD_2
                    ICONST_0
                    AALOAD
                    CHECKCAST org.argouml.uml.util.namespace.StringNamespace
                    ALOAD_2
                    ICONST_1
                    AALOAD
                    CHECKCAST java.util.Stack
                    ALOAD_2
                    ICONST_2
                    AALOAD
                    CHECKCAST org.aspectj.lang.JoinPoint
                    INVOKESTATIC org.argouml.uml.util.namespace.StringNamespace.peek_aroundBody18 (Lorg/argouml/uml/util/namespace/StringNamespace;Ljava/util/Stack;Lorg/aspectj/lang/JoinPoint;)Ljava/lang/Object;
                    ARETURN
  end public Object run(Object[])
end public class org.argouml.uml.util.namespace.StringNamespace$AjcClosure19

public class org.argouml.uml.util.namespace.StringNamespace$AjcClosure21 extends org.aspectj.runtime.internal.AroundClosure:
  public void <init>(Object[]):
                    ALOAD_0
                    ALOAD_1
                    INVOKESPECIAL org.aspectj.runtime.internal.AroundClosure.<init> ([Ljava/lang/Object;)V
                    RETURN
  end public void <init>(Object[])

  public Object run(Object[]):
                    ALOAD_0
                    GETFIELD org.aspectj.runtime.internal.AroundClosure.state [Ljava/lang/Object;
                    ASTORE_2
                    ALOAD_2
                    ICONST_0
                    AALOAD
                    CHECKCAST org.argouml.uml.util.namespace.StringNamespace
                    ALOAD_2
                    ICONST_1
                    AALOAD
                    CHECKCAST java.util.Stack
                    ALOAD_2
                    ICONST_2
                    AALOAD
                    CHECKCAST org.aspectj.lang.JoinPoint
                    INVOKESTATIC org.argouml.uml.util.namespace.StringNamespace.peek_aroundBody20 (Lorg/argouml/uml/util/namespace/StringNamespace;Ljava/util/Stack;Lorg/aspectj/lang/JoinPoint;)Ljava/lang/Object;
                    ARETURN
  end public Object run(Object[])
end public class org.argouml.uml.util.namespace.StringNamespace$AjcClosure21

public class org.argouml.uml.util.namespace.StringNamespace$AjcClosure23 extends org.aspectj.runtime.internal.AroundClosure:
  public void <init>(Object[]):
                    ALOAD_0
                    ALOAD_1
                    INVOKESPECIAL org.aspectj.runtime.internal.AroundClosure.<init> ([Ljava/lang/Object;)V
                    RETURN
  end public void <init>(Object[])

  public Object run(Object[]):
                    ALOAD_0
                    GETFIELD org.aspectj.runtime.internal.AroundClosure.state [Ljava/lang/Object;
                    ASTORE_2
                    ALOAD_2
                    ICONST_0
                    AALOAD
                    CHECKCAST org.argouml.uml.util.namespace.StringNamespace
                    ALOAD_2
                    ICONST_1
                    AALOAD
                    CHECKCAST org.aspectj.lang.JoinPoint
                    INVOKESTATIC org.argouml.uml.util.namespace.StringNamespace.peekNamespaceElement_aroundBody22 (Lorg/argouml/uml/util/namespace/StringNamespace;Lorg/aspectj/lang/JoinPoint;)Lorg/argouml/uml/util/namespace/NamespaceElement;
                    ARETURN
  end public Object run(Object[])
end public class org.argouml.uml.util.namespace.StringNamespace$AjcClosure23

public class org.argouml.uml.util.namespace.StringNamespace$AjcClosure25 extends org.aspectj.runtime.internal.AroundClosure:
  public void <init>(Object[]):
                    ALOAD_0
                    ALOAD_1
                    INVOKESPECIAL org.aspectj.runtime.internal.AroundClosure.<init> ([Ljava/lang/Object;)V
                    RETURN
  end public void <init>(Object[])

  public Object run(Object[]):
                    ALOAD_0
                    GETFIELD org.aspectj.runtime.internal.AroundClosure.state [Ljava/lang/Object;
                    ASTORE_2
                    ALOAD_2
                    ICONST_0
                    AALOAD
                    CHECKCAST org.argouml.uml.util.namespace.StringNamespace
                    ALOAD_2
                    ICONST_1
                    AALOAD
                    CHECKCAST java.util.Stack
                    ALOAD_2
                    ICONST_2
                    AALOAD
                    ALOAD_2
                    ICONST_3
                    AALOAD
                    CHECKCAST org.aspectj.lang.JoinPoint
                    INVOKESTATIC org.argouml.uml.util.namespace.StringNamespace.push_aroundBody24 (Lorg/argouml/uml/util/namespace/StringNamespace;Ljava/util/Stack;Ljava/lang/Object;Lorg/aspectj/lang/JoinPoint;)Ljava/lang/Object;
                    ARETURN
  end public Object run(Object[])
end public class org.argouml.uml.util.namespace.StringNamespace$AjcClosure25

public class org.argouml.uml.util.namespace.StringNamespace$AjcClosure27 extends org.aspectj.runtime.internal.AroundClosure:
  public void <init>(Object[]):
                    ALOAD_0
                    ALOAD_1
                    INVOKESPECIAL org.aspectj.runtime.internal.AroundClosure.<init> ([Ljava/lang/Object;)V
                    RETURN
  end public void <init>(Object[])

  public Object run(Object[]):
                    ALOAD_0
                    GETFIELD org.aspectj.runtime.internal.AroundClosure.state [Ljava/lang/Object;
                    ASTORE_2
                    ALOAD_2
                    ICONST_0
                    AALOAD
                    CHECKCAST org.argouml.uml.util.namespace.StringNamespace
                    ALOAD_2
                    ICONST_1
                    AALOAD
                    CHECKCAST java.util.Stack
                    ALOAD_2
                    ICONST_2
                    AALOAD
                    ALOAD_2
                    ICONST_3
                    AALOAD
                    CHECKCAST org.aspectj.lang.JoinPoint
                    INVOKESTATIC org.argouml.uml.util.namespace.StringNamespace.push_aroundBody26 (Lorg/argouml/uml/util/namespace/StringNamespace;Ljava/util/Stack;Ljava/lang/Object;Lorg/aspectj/lang/JoinPoint;)Ljava/lang/Object;
                    ARETURN
  end public Object run(Object[])
end public class org.argouml.uml.util.namespace.StringNamespace$AjcClosure27

public class org.argouml.uml.util.namespace.StringNamespace$AjcClosure29 extends org.aspectj.runtime.internal.AroundClosure:
  public void <init>(Object[]):
                    ALOAD_0
                    ALOAD_1
                    INVOKESPECIAL org.aspectj.runtime.internal.AroundClosure.<init> ([Ljava/lang/Object;)V
                    RETURN
  end public void <init>(Object[])

  public Object run(Object[]):
                    ALOAD_0
                    GETFIELD org.aspectj.runtime.internal.AroundClosure.state [Ljava/lang/Object;
                    ASTORE_2
                    ALOAD_2
                    ICONST_0
                    AALOAD
                    CHECKCAST org.argouml.uml.util.namespace.StringNamespace
                    ALOAD_2
                    ICONST_1
                    AALOAD
                    CHECKCAST java.lang.String
                    ALOAD_2
                    ICONST_2
                    AALOAD
                    CHECKCAST org.aspectj.lang.JoinPoint
                    INVOKESTATIC org.argouml.uml.util.namespace.StringNamespace.pushNamespaceElement_aroundBody28 (Lorg/argouml/uml/util/namespace/StringNamespace;Ljava/lang/String;Lorg/aspectj/lang/JoinPoint;)V
                    ACONST_NULL
                    ARETURN
  end public Object run(Object[])
end public class org.argouml.uml.util.namespace.StringNamespace$AjcClosure29

public class org.argouml.uml.util.namespace.StringNamespace$AjcClosure31 extends org.aspectj.runtime.internal.AroundClosure:
  public void <init>(Object[]):
                    ALOAD_0
                    ALOAD_1
                    INVOKESPECIAL org.aspectj.runtime.internal.AroundClosure.<init> ([Ljava/lang/Object;)V
                    RETURN
  end public void <init>(Object[])

  public Object run(Object[]):
                    ALOAD_0
                    GETFIELD org.aspectj.runtime.internal.AroundClosure.state [Ljava/lang/Object;
                    ASTORE_2
                    ALOAD_2
                    ICONST_0
                    AALOAD
                    CHECKCAST org.argouml.uml.util.namespace.StringNamespace
                    ALOAD_2
                    ICONST_1
                    AALOAD
                    CHECKCAST java.util.Stack
                    ALOAD_2
                    ICONST_2
                    AALOAD
                    CHECKCAST org.aspectj.lang.JoinPoint
                    INVOKESTATIC org.argouml.uml.util.namespace.StringNamespace.pop_aroundBody30 (Lorg/argouml/uml/util/namespace/StringNamespace;Ljava/util/Stack;Lorg/aspectj/lang/JoinPoint;)Ljava/lang/Object;
                    ARETURN
  end public Object run(Object[])
end public class org.argouml.uml.util.namespace.StringNamespace$AjcClosure31

public class org.argouml.uml.util.namespace.StringNamespace$AjcClosure33 extends org.aspectj.runtime.internal.AroundClosure:
  public void <init>(Object[]):
                    ALOAD_0
                    ALOAD_1
                    INVOKESPECIAL org.aspectj.runtime.internal.AroundClosure.<init> ([Ljava/lang/Object;)V
                    RETURN
  end public void <init>(Object[])

  public Object run(Object[]):
                    ALOAD_0
                    GETFIELD org.aspectj.runtime.internal.AroundClosure.state [Ljava/lang/Object;
                    ASTORE_2
                    ALOAD_2
                    ICONST_0
                    AALOAD
                    CHECKCAST org.argouml.uml.util.namespace.StringNamespace
                    ALOAD_2
                    ICONST_1
                    AALOAD
                    CHECKCAST java.util.Stack
                    ALOAD_2
                    ICONST_2
                    AALOAD
                    CHECKCAST org.aspectj.lang.JoinPoint
                    INVOKESTATIC org.argouml.uml.util.namespace.StringNamespace.pop_aroundBody32 (Lorg/argouml/uml/util/namespace/StringNamespace;Ljava/util/Stack;Lorg/aspectj/lang/JoinPoint;)Ljava/lang/Object;
                    ARETURN
  end public Object run(Object[])
end public class org.argouml.uml.util.namespace.StringNamespace$AjcClosure33

public class org.argouml.uml.util.namespace.StringNamespace$AjcClosure35 extends org.aspectj.runtime.internal.AroundClosure:
  public void <init>(Object[]):
                    ALOAD_0
                    ALOAD_1
                    INVOKESPECIAL org.aspectj.runtime.internal.AroundClosure.<init> ([Ljava/lang/Object;)V
                    RETURN
  end public void <init>(Object[])

  public Object run(Object[]):
                    ALOAD_0
                    GETFIELD org.aspectj.runtime.internal.AroundClosure.state [Ljava/lang/Object;
                    ASTORE_2
                    ALOAD_2
                    ICONST_0
                    AALOAD
                    CHECKCAST org.argouml.uml.util.namespace.StringNamespace
                    ALOAD_2
                    ICONST_1
                    AALOAD
                    CHECKCAST org.aspectj.lang.JoinPoint
                    INVOKESTATIC org.argouml.uml.util.namespace.StringNamespace.popNamespaceElement_aroundBody34 (Lorg/argouml/uml/util/namespace/StringNamespace;Lorg/aspectj/lang/JoinPoint;)Lorg/argouml/uml/util/namespace/NamespaceElement;
                    ARETURN
  end public Object run(Object[])
end public class org.argouml.uml.util.namespace.StringNamespace$AjcClosure35
 -- (BCException) Can't determine real target of clone() when processing instruction invokestatic[184](size3) 260.  Perhaps avoid selecting clone with your pointcut?
when implementing on shadow method-call(java.lang.Object java.lang.Object.clone())
when weaving type org.argouml.uml.util.namespace.StringNamespace
when weaving classes 
when weaving 

Can't determine real target of clone() when processing instruction invokestatic[184](size3) 260.  Perhaps avoid selecting clone with your pointcut?
when implementing on shadow method-call(java.lang.Object java.lang.Object.clone())
when weaving type org.argouml.uml.util.namespace.StringNamespace
when weaving classes 
when weaving 

org.aspectj.weaver.BCException: Can't determine real target of clone() when processing instruction invokestatic[184](size3) 260.  Perhaps avoid selecting clone with your pointcut?
when implementing on shadow method-call(java.lang.Object java.lang.Object.clone())
when weaving type org.argouml.uml.util.namespace.StringNamespace
when weaving classes 
when weaving 

	at org.aspectj.weaver.bcel.BcelShadow.ensureTargetTypeIsCorrect(BcelShadow.java:1313)
	at org.aspectj.weaver.bcel.BcelShadow.createShadowMethodGen(BcelShadow.java:3231)
	at org.aspectj.weaver.bcel.BcelShadow.extractShadowInstructionsIntoNewMethod(BcelShadow.java:3127)
	at org.aspectj.weaver.bcel.BcelShadow.weaveAroundClosure(BcelShadow.java:2829)
	at org.aspectj.weaver.bcel.BcelAdvice.implementOn(BcelAdvice.java:343)
	at org.aspectj.weaver.Shadow.implementMungers(Shadow.java:632)
	at org.aspectj.weaver.Shadow.implement(Shadow.java:547)
	at org.aspectj.weaver.bcel.BcelClassWeaver.implement(BcelClassWeaver.java:3289)
	at org.aspectj.weaver.bcel.BcelClassWeaver.weave(BcelClassWeaver.java:497)
	at org.aspectj.weaver.bcel.BcelClassWeaver.weave(BcelClassWeaver.java:101)
	at org.aspectj.weaver.bcel.BcelWeaver.weave(BcelWeaver.java:1689)
	at org.aspectj.weaver.bcel.BcelWeaver.weaveWithoutDump(BcelWeaver.java:1633)
	at org.aspectj.weaver.bcel.BcelWeaver.weaveAndNotify(BcelWeaver.java:1398)
	at org.aspectj.weaver.bcel.BcelWeaver.weave(BcelWeaver.java:1184)
	at org.aspectj.weaver.tools.WeavingAdaptor.getWovenBytes(WeavingAdaptor.java:527)
	at org.aspectj.weaver.tools.WeavingAdaptor.weaveClass(WeavingAdaptor.java:363)
	at org.aspectj.weaver.loadtime.Aj.preProcess(Aj.java:121)
	at org.aspectj.weaver.loadtime.ClassPreProcessorAgentAdapter.transform(ClassPreProcessorAgentAdapter.java:54)
	at java.instrument/java.lang.instrument.ClassFileTransformer.transform(ClassFileTransformer.java:246)
	at java.instrument/sun.instrument.TransformerManager.transform(TransformerManager.java:188)
	at java.instrument/sun.instrument.InstrumentationImpl.transform(InstrumentationImpl.java:563)
	at java.base/java.lang.ClassLoader.defineClass1(Native Method)
	at java.base/java.lang.ClassLoader.defineClass(ClassLoader.java:1017)
	at java.base/java.security.SecureClassLoader.defineClass(SecureClassLoader.java:174)
	at java.base/jdk.internal.loader.BuiltinClassLoader.defineClass(BuiltinClassLoader.java:800)
	at java.base/jdk.internal.loader.BuiltinClassLoader.findClassOnClassPathOrNull(BuiltinClassLoader.java:698)
	at java.base/jdk.internal.loader.BuiltinClassLoader.loadClassOrNull(BuiltinClassLoader.java:621)
	at java.base/jdk.internal.loader.BuiltinClassLoader.loadClass(BuiltinClassLoader.java:579)
	at java.base/jdk.internal.loader.ClassLoaders$AppClassLoader.loadClass(ClassLoaders.java:178)
	at java.base/java.lang.ClassLoader.loadClass(ClassLoader.java:522)
	at java.base/java.lang.Class.forName0(Native Method)
	at java.base/java.lang.Class.forName(Class.java:398)
	at org.aspectj.runtime.reflect.Factory.makeClass(Factory.java:70)
	at org.aspectj.runtime.reflect.Factory.makeMethodSig(Factory.java:189)
	at org.argouml.uml.ui.TabStyle.ajc$preClinit(TabStyle.java:1)
	at org.argouml.uml.ui.TabStyle.<clinit>(TabStyle.java)
	at org.argouml.uml.ui.InitUmlUI.getDetailsTabs_aroundBody30(InitUmlUI.java:64)
	at org.argouml.uml.ui.InitUmlUI$AjcClosure31.run(InitUmlUI.java:1)
	at org.aspectj.runtime.reflect.JoinPointImpl.proceed(JoinPointImpl.java:149)
	at kieker.monitoring.probe.aspectj.flow.operationExecution.AbstractAspect.operation(AbstractAspect.java:76)
	at org.argouml.uml.ui.InitUmlUI.getDetailsTabs(InitUmlUI.java:60)
	at org.argouml.application.SubsystemUtility.getDetailsTabs_aroundBody52(SubsystemUtility.java:74)
	at org.argouml.application.SubsystemUtility$AjcClosure53.run(SubsystemUtility.java:1)
	at org.aspectj.runtime.reflect.JoinPointImpl.proceed(JoinPointImpl.java:149)
	at kieker.monitoring.probe.aspectj.flow.operationCallObject.AbstractAspect.static2memberOperation(AbstractAspect.java:122)
	at org.argouml.application.SubsystemUtility.getDetailsTabs_aroundBody54(SubsystemUtility.java:1)
	at org.argouml.application.SubsystemUtility$AjcClosure55.run(SubsystemUtility.java:1)
	at org.aspectj.runtime.reflect.JoinPointImpl.proceed(JoinPointImpl.java:149)
	at kieker.monitoring.probe.aspectj.flow.operationCall.AbstractAspect.static2memberOperation(AbstractAspect.java:119)
	at org.argouml.application.SubsystemUtility.initSubsystem_aroundBody80(SubsystemUtility.java:74)
	at org.argouml.application.SubsystemUtility$AjcClosure81.run(SubsystemUtility.java:1)
	at org.aspectj.runtime.reflect.JoinPointImpl.proceed(JoinPointImpl.java:149)
	at kieker.monitoring.probe.aspectj.flow.operationExecution.AbstractAspect.staticOperation(AbstractAspect.java:115)
	at org.argouml.application.SubsystemUtility.initSubsystem(SubsystemUtility.java:63)
	at org.argouml.application.Main.initSubsystem_aroundBody526(Main.java:430)
	at org.argouml.application.Main$AjcClosure527.run(Main.java:1)
	at org.aspectj.runtime.reflect.JoinPointImpl.proceed(JoinPointImpl.java:149)
	at kieker.monitoring.probe.aspectj.flow.operationCallObject.AbstractAspect.static2staticOperation(AbstractAspect.java:201)
	at org.argouml.application.Main.initSubsystem_aroundBody528(Main.java:1)
	at org.argouml.application.Main$AjcClosure529.run(Main.java:1)
	at org.aspectj.runtime.reflect.JoinPointImpl.proceed(JoinPointImpl.java:149)
	at kieker.monitoring.probe.aspectj.flow.operationCall.AbstractAspect.static2staticOperation(AbstractAspect.java:196)
	at org.argouml.application.Main.initializeSubsystems_aroundBody546(Main.java:430)
	at org.argouml.application.Main$AjcClosure547.run(Main.java:1)
	at org.aspectj.runtime.reflect.JoinPointImpl.proceed(JoinPointImpl.java:149)
	at kieker.monitoring.probe.aspectj.flow.operationExecution.AbstractAspect.staticOperation(AbstractAspect.java:115)
	at org.argouml.application.Main.initializeSubsystems(Main.java:403)
	at org.argouml.application.Main.initializeSubsystems_aroundBody52(Main.java:182)
	at org.argouml.application.Main$AjcClosure53.run(Main.java:1)
	at org.aspectj.runtime.reflect.JoinPointImpl.proceed(JoinPointImpl.java:149)
	at kieker.monitoring.probe.aspectj.flow.operationCallObject.AbstractAspect.static2staticOperation(AbstractAspect.java:201)
	at org.argouml.application.Main.initializeSubsystems_aroundBody54(Main.java:1)
	at org.argouml.application.Main$AjcClosure55.run(Main.java:1)
	at org.aspectj.runtime.reflect.JoinPointImpl.proceed(JoinPointImpl.java:149)
	at kieker.monitoring.probe.aspectj.flow.operationCall.AbstractAspect.static2staticOperation(AbstractAspect.java:196)
	at org.argouml.application.Main.main_aroundBody224(Main.java:182)
	at org.argouml.application.Main$AjcClosure225.run(Main.java:1)
	at org.aspectj.runtime.reflect.JoinPointImpl.proceed(JoinPointImpl.java:149)
	at kieker.monitoring.probe.aspectj.flow.operationExecution.AbstractAspect.staticOperation(AbstractAspect.java:115)
	at org.argouml.application.Main.main(Main.java:153)

